Workbook

Sheet 01 Cover
A1: ABC PRIVATE LIMITED
A5: MONTHLY FINANCIAL REPORT
A8: August 2026 | FY 2026–27
C11: Prepared By | D11: Finance Department
C12: Reviewed By | D12: Management
C13: Report Date | D13: 31-Aug-2026
C14: Version | D14: 1.0
C15: Status | D15: Final
C16: Confidentiality | D16: Management Use Only
A19: CONFIDENTIAL – MANAGEMENT USE ONLY

Sheet 02 Executive Dashboard
A1: EXECUTIVE DASHBOARD
A2: Monthly Financial Report | August 2026 | Confidential | H2: ← Dashboard | I2: 🏠 Home | J2: → Control & Assumptions
A4: KPI | B4: Actual | C4: Budget | D4: Variance
A5: Revenue | B5: ='05 P&L'!B9 -> 12400000 | C5: ='05 P&L'!C9 -> 11800000 | D5: ='05 P&L'!B9/'05 P&L'!C9-1 -> 0.050847458
A6: Gross Profit | B6: ='05 P&L'!B16 -> 7700000 | C6: ='05 P&L'!C16 -> 7200000 | D6: ='05 P&L'!B16/'05 P&L'!C16-1 -> 0.069444444
A7: EBITDA | B7: ='05 P&L'!B28 -> 3940000 | C7: ='05 P&L'!C28 -> 3630000 | D7: ='05 P&L'!B28/'05 P&L'!C28-1 -> 0.085399449
A8: Net Profit | B8: ='05 P&L'!B32 -> 2790000 | C8: ='05 P&L'!C32 -> 2550000 | D8: ='05 P&L'!B32/'05 P&L'!C32-1 -> 0.094117647
A9: Cash Balance | B9: ='04 Data Input'!G6 -> 8300000 | C9: =7800000 -> 7800000 | D9: ='04 Data Input'!G6/C9-1 -> 0.064102564
A11: Management Summary
A12: Key Highlights | B12: Revenue above budget; EBITDA strengthened
A13: Key Concerns | B13: Salaries above budget; monitor receivables
A14: Management Actions | B14: Cost optimization, collections, revenue initiatives
A15: Model Status | B15: ='06 Balance Sheet'!B30 -> OK ✓ | C15: Cash Flow | D15: ='07 Cash Flow'!B28 -> OK ✓
A16: Input Guide | B16: Yellow = Input | Blue = Formula | Green = Output
A38: Month | B38: Revenue | C38: EBITDA | D38: Net Profit
A39: Jan | B39: =INDEX('14 Monthly Trends'!$B$5:$M$5,1,ROW()-39) -> 10000000 | C39: =INDEX('14 Monthly Trends'!$B$7:$M$7,1,ROW()-39) -> 2100000 | D39: =INDEX('14 Monthly Trends'!$B$8:$M$8,1,ROW()-39) -> 1300000
A40: Feb | B40: =INDEX('14 Monthly Trends'!$B$5:$M$5,1,ROW()-39) -> 10000000 | C40: =INDEX('14 Monthly Trends'!$B$7:$M$7,1,ROW()-39) -> 2000000 | D40: =INDEX('14 Monthly Trends'!$B$8:$M$8,1,ROW()-39) -> 1100000
A41: Mar | B41: =INDEX('14 Monthly Trends'!$B$5:$M$5,1,ROW()-39) -> 10500000 | C41: =INDEX('14 Monthly Trends'!$B$7:$M$7,1,ROW()-39) -> 2100000 | D41: =INDEX('14 Monthly Trends'!$B$8:$M$8,1,ROW()-39) -> 1200000
A42: Apr | B42: =INDEX('14 Monthly Trends'!$B$5:$M$5,1,ROW()-39) -> 11000000 | C42: =INDEX('14 Monthly Trends'!$B$7:$M$7,1,ROW()-39) -> 2200000 | D42: =INDEX('14 Monthly Trends'!$B$8:$M$8,1,ROW()-39) -> 1300000
A43: May | B43: =INDEX('14 Monthly Trends'!$B$5:$M$5,1,ROW()-39) -> 11400000 | C43: =INDEX('14 Monthly Trends'!$B$7:$M$7,1,ROW()-39) -> 2300000 | D43: =INDEX('14 Monthly Trends'!$B$8:$M$8,1,ROW()-39) -> 1400000
A44: Jun | B44: =INDEX('14 Monthly Trends'!$B$5:$M$5,1,ROW()-39) -> 12000000 | C44: =INDEX('14 Monthly Trends'!$B$7:$M$7,1,ROW()-39) -> 2500000 | D44: =INDEX('14 Monthly Trends'!$B$8:$M$8,1,ROW()-39) -> 1500000
A45: Jul | B45: =INDEX('14 Monthly Trends'!$B$5:$M$5,1,ROW()-39) -> 12400000 | C45: =INDEX('14 Monthly Trends'!$B$7:$M$7,1,ROW()-39) -> 2800000 | D45: =INDEX('14 Monthly Trends'!$B$8:$M$8,1,ROW()-39) -> 1700000
A46: Aug | B46: =INDEX('14 Monthly Trends'!$B$5:$M$5,1,ROW()-39) -> 12100000 | C46: =INDEX('14 Monthly Trends'!$B$7:$M$7,1,ROW()-39) -> 2600000 | D46: =INDEX('14 Monthly Trends'!$B$8:$M$8,1,ROW()-39) -> 1550000
A47: Sep | B47: =INDEX('14 Monthly Trends'!$B$5:$M$5,1,ROW()-39) -> 12400000 | C47: =INDEX('14 Monthly Trends'!$B$7:$M$7,1,ROW()-39) -> 2800000 | D47: =INDEX('14 Monthly Trends'!$B$8:$M$8,1,ROW()-39) -> 1700000
A48: Oct | B48: =INDEX('14 Monthly Trends'!$B$5:$M$5,1,ROW()-39) -> 12800000 | C48: =INDEX('14 Monthly Trends'!$B$7:$M$7,1,ROW()-39) -> 3000000 | D48: =INDEX('14 Monthly Trends'!$B$8:$M$8,1,ROW()-39) -> 1850000
A49: Nov | B49: =INDEX('14 Monthly Trends'!$B$5:$M$5,1,ROW()-39) -> 13100000 | C49: =INDEX('14 Monthly Trends'!$B$7:$M$7,1,ROW()-39) -> 3150000 | D49: =INDEX('14 Monthly Trends'!$B$8:$M$8,1,ROW()-39) -> 1950000
A50: Dec | B50: =INDEX('14 Monthly Trends'!$B$5:$M$5,1,ROW()-39) -> 13400000 | C50: =INDEX('14 Monthly Trends'!$B$7:$M$7,1,ROW()-39) -> 3300000 | D50: =INDEX('14 Monthly Trends'!$B$8:$M$8,1,ROW()-39) -> 2050000

Sheet 03 Control & Assumptions
A1: CONTROL & ASSUMPTIONS
A2: Monthly Financial Report | August 2026 | Confidential | H2: ← Dashboard | I2: 🏠 Home | J2: → Data Input
A4: Report Controls
A5: Company Name | B5: ABC PRIVATE LIMITED
A6: Reporting Month | B6: August 2026
A7: Financial Year | B7: FY 2026–27
A8: Currency | B8: INR
A9: Prepared By | B9: Finance Department
A10: Reviewed By | B10: Management
A11: Scenario | B11: Budget
A14: Assumptions
A15: Revenue Recognition | B15: Accrual basis
A16: Depreciation Method | B16: Straight-line
A17: Tax Rate | B17: 0.25
A18: FX Assumption | B18: No material FX exposure
A19: Budget Assumption | B19: Approved FY26–27 budget
A20: Headcount Assumption | B20: New hires per approved plan
A21: Input Convention | B21: Yellow cells are editable

Sheet 04 Data Input
A1: DATA INPUT
A2: Yellow cells = user input | Blue cells = formulas | Green cells = final output | H2: ← Dashboard | I2: 🏠 Home | J2: → P&L
A4: Current Month Actuals & Budget
A5: Account | B5: Actual | C5: Budget | D5: Category | F5: Balance Sheet Input | G5: Actual
A6: Product Revenue | B6: 10200000 | C6: 9700000 | D6: Revenue | F6: Cash & Bank | G6: 8300000
A7: Service Revenue | B7: 2000000 | C7: 1900000 | D7: Revenue | F7: Accounts Receivable | G7: 4200000
A8: Other Revenue | B8: 200000 | C8: 200000 | D8: Revenue | F8: Inventory | G8: 2300000
A9: Material Cost | B9: 1800000 | C9: 1750000 | D9: COGS | F9: Prepaid Expenses | G9: 350000
A10: Direct Labour | B10: 1100000 | C10: 1050000 | D10: COGS | F10: Other Current Assets | G10: 250000
A11: Production Cost | B11: 1050000 | C11: 1000000 | D11: COGS | F11: PPE | G11: 9500000
A12: Other COGS | B12: 750000 | C12: 800000 | D12: COGS | F12: Intangible Assets | G12: 900000
A13: Salaries | B13: 1900000 | C13: 1800000 | D13: Opex | F13: Other Assets | G13: 300000
A14: Rent | B14: 520000 | C14: 500000 | D14: Opex | F14: Accounts Payable | G14: 3100000
A15: Marketing | B15: 350000 | C15: 400000 | D15: Opex | F15: Short-term Borrowings | G15: 1200000
A16: IT | B16: 220000 | C16: 200000 | D16: Opex | F16: Accrued Expenses | G16: 650000
A17: Travel | B17: 130000 | C17: 120000 | D17: Opex | F17: Taxes Payable | G17: 450000
... A20: Insurance | B20: 65000 | C20: 60000 | D20: Opex | F20: Share Capital | G20: 8000000
A21: Other Opex | B21: 300000 | C21: 250000 | D21: Opex
A22: Depreciation | B22: 250000 | C22: 240000 | D22: Below EBITDA
A23: Interest | B23: 350000 | C23: 340000 | D23: Below EBITDA
A24: Tax | B24: 550000 | C24: 500000 | D24: Below EBITDA

Sheet 05 P&L
A1: MONTHLY PROFIT & LOSS
A2: Monthly Financial Report | August 2026 | Confidential | H2: ← Dashboard | I2: 🏠 Home | J2: → Balance Sheet
A4: Particular | B4: Actual | C4: Budget | D4: Variance
A5: Revenue
A6: Product Revenue | B6: ='04 Data Input'!B6 -> 10200000 | C6: ='04 Data Input'!C6 -> 9700000 | D6: =B6-C6 -> 500000
A7: Service Revenue | B7: ='04 Data Input'!B7 -> 2000000 | C7: ='04 Data Input'!C7 -> 1900000 | D7: =B7-C7 -> 100000
A8: Other Revenue | B8: ='04 Data Input'!B8 -> 200000 | C8: ='04 Data Input'!C8 -> 200000 | D8: =B8-C8 -> 0
A9: Total Revenue | B9: =SUM(B6:B8) -> 12400000 | C9: =SUM(C6:C8) -> 11800000 | D9: =B9-C9 -> 600000
A10: Cost of Sales
A11: Material Cost | B11: ='04 Data Input'!B9 -> 1800000 | C11: ='04 Data Input'!C9 -> 1750000 | D11: =B11-C11 -> 50000
A12: Direct Labour | B12: ='04 Data Input'!B10 -> 1100000 | C12: ='04 Data Input'!C10 -> 1050000 | D12: =B12-C12 -> 50000
A13: Production Cost | B13: ='04 Data Input'!B11 -> 1050000 | C13: ='04 Data Input'!C11 -> 1000000 | D13: =B13-C13 -> 50000
A14: Other COGS | B14: ='04 Data Input'!B12 -> 750000 | C14: ='04 Data Input'!C12 -> 800000 | D14: =B14-C14 -> -50000
A15: Total COGS | B15: =SUM(B11:B14) -> 4700000 | C15: =SUM(C11:C14) -> 4600000 | D15: =B15-C15 -> 100000
A16: Gross Profit | B16: =B9-B15 -> 7700000 | C16: =C9-C15 -> 7200000 | D16: =B16-C16 -> 500000
A17: Operating Expenses
A18: Salaries | B18: ='04 Data Input'!B13 -> 1900000 | C18: ='04 Data Input'!C13 -> 1800000 | D18: =B18-C18 -> 100000
A19: Rent | B19: ='04 Data Input'!B14 -> 520000 | C19: ='04 Data Input'!C14 -> 500000 | D19: =B19-C19 -> 20000
A20: Marketing | B20: ='04 Data Input'!B15 -> 350000 | C20: ='04 Data Input'!C15 -> 400000 | D20: =B20-C20 -> -50000
A21: IT | B21: ='04 Data Input'!B16 -> 220000 | C21: ='04 Data Input'!C16 -> 200000 | D21: =B21-C21 -> 20000
A22: Travel | B22: ='04 Data Input'!B17 -> 130000 | C22: ='04 Data Input'!C17 -> 120000 | D22: =B22-C22 -> 10000
A23: Professional Fees | B23: ='04 Data Input'!B18 -> 180000 | C23: ='04 Data Input'!C18 -> 150000 | D23: =B23-C23 -> 30000
A24: Utilities | B24: ='04 Data Input'!B19 -> 95000 | C24: ='04 Data Input'!C19 -> 90000 | D24: =B24-C24 -> 5000
A25: Insurance | B25: ='04 Data Input'!B20 -> 65000 | C25: ='04 Data Input'!C20 -> 60000 | D25: =B25-C25 -> 5000
A26: Other Opex | B26: ='04 Data Input'!B21 -> 300000 | C26: ='04 Data Input'!C21 -> 250000 | D26: =B26-C26 -> 50000
A27: Total Operating Expenses | B27: =SUM(B18:B26) -> 3760000 | C27: =SUM(C18:C26) -> 3570000 | D27: =B27-C27 -> 190000
A28: EBITDA | B28: =B16-B27 -> 3940000 | C28: =C16-C27 -> 3630000 | D28: =B28-C28 -> 310000
A29: Depreciation | B29: ='04 Data Input'!B22 -> 250000 | C29: ='04 Data Input'!C22 -> 240000 | D29: =B29-C29 -> 10000
A30: Interest | B30: ='04 Data Input'!B23 -> 350000 | C30: ='04 Data Input'!C23 -> 340000 | D30: =B30-C30 -> 10000
A31: Tax | B31: ='04 Data Input'!B24 -> 550000 | C31: ='04 Data Input'!C24 -> 500000 | D31: =B31-C31 -> 50000
A32: Net Profit / Loss | B32: =B28-B29-B30-B31 -> 2790000 | C32: =C28-C29-C30-C31 -> 2550000 | D32: =B32-C32 -> 240000

Sheet 06 Balance Sheet
A1: MONTHLY BALANCE SHEET
A2: Monthly Financial Report | August 2026 | Confidential | H2: ← Dashboard | I2: 🏠 Home | J2: → Cash Flow
A4: Particular | B4: Amount
A5: Assets | B5: =SUM(B7:B11)+SUM(B13:B15) -> 26100000
A6: Current Assets
A7: Cash & Bank | B7: ='04 Data Input'!G6 -> 8300000
A8: Accounts Receivable | B8: ='04 Data Input'!G7 -> 4200000
A9: Inventory | B9: ='04 Data Input'!G8 -> 2300000
A10: Prepaid Expenses | B10: ='04 Data Input'!G9 -> 350000
A11: Other Current Assets | B11: ='04 Data Input'!G10 -> 250000
A12: Non-Current Assets
A13: Property, Plant & Equipment | B13: ='04 Data Input'!G11 -> 9500000
A14: Intangible Assets | B14: ='04 Data Input'!G12 -> 900000
A15: Other Assets | B15: ='04 Data Input'!G13 -> 300000
A16: Liabilities | B16: =SUM(B18:B21)+SUM(B23:B24) -> 12250000
A17: Current Liabilities
A18: Accounts Payable | B18: ='04 Data Input'!G14 -> 3100000
A19: Short-term Borrowings | B19: ='04 Data Input'!G15 -> 1200000
A20: Accrued Expenses | B20: ='04 Data Input'!G16 -> 650000
A21: Taxes Payable | B21: ='04 Data Input'!G17 -> 450000
A22: Non-Current Liabilities
A23: Long-term Debt | B23: ='04 Data Input'!G18 -> 6500000
A24: Other Long-term Liabilities | B24: ='04 Data Input'!G19 -> 350000
A25: Equity | B25: =B26+B27+B28 -> 13850000
A26: Share Capital | B26: ='04 Data Input'!G20 -> 8000000
A27: Retained Earnings | B27: =B5-B16-B26-B28 -> 3060000
A28: Current Year Profit | B28: ='05 P&L'!B32 -> 2790000
A29: Total Liabilities + Equity | B29: =B16+B25 -> 26100000
A30: Balance Check | B30: =IF(ABS(B5-B29)<1,"OK ✓","CHECK") -> OK ✓

Sheet 07 Cash Flow
A1: CASH FLOW STATEMENT
A2: Monthly Financial Report | August 2026 | Confidential | H2: ← Dashboard | I2: 🏠 Home | J2: → Budget vs Actual
A4: Particular | B4: Amount
A5: Operating Activities
A6: Net Profit | B6: ='05 P&L'!B32 -> 2790000
A7: Depreciation | B7: ='05 P&L'!B29 -> 250000
A8: Change in Receivables | B8: -200000
A9: Change in Inventory | B9: -100000
A10: Change in Payables | B10: 150000
A11: Other Working Capital Changes | B11: -50000
A12: Net Cash from Operations | B12: =SUM(B6:B11) -> 2840000
A13: Investing Activities
A14: Capital Expenditure | B14: -600000
A15: Asset Purchases | B15: -100000
A16: Asset Sales | B16: 0
A17: Investments | B17: 0
A18: Net Cash from Investing | B18: =SUM(B14:B17) -> -700000
A19: Financing Activities
A20: Loan Proceeds | B20: 500000
A21: Loan Repayment | B21: -300000
A22: Equity Injection | B22: 0
A23: Dividends | B23: 0
A24: Net Cash from Financing | B24: =SUM(B20:B23) -> 200000
A25: Net Change in Cash | B25: =B12+B18+B24 -> 2340000
A26: Opening Cash | B26: ='04 Data Input'!G6-B25 -> 5960000
A27: Closing Cash | B27: =B25+B26 -> 8300000
A28: Cash Reconciliation | B28: =IF(ABS(B27-'04 Data Input'!G6)<1,"OK ✓","CHECK") -> OK ✓

Sheet 08 Budget vs Actual
A1: BUDGET VS ACTUAL
A2: Monthly Financial Report | August 2026 | Confidential | H2: ← Dashboard | I2: 🏠 Home | J2: → KPI Analysis
A4: Particular | B4: Budget | C4: Actual | D4: Variance | E4: Variance % | F4: Status
A5: Revenue | B5: ='05 P&L'!C9 -> 11800000 | C5: ='05 P&L'!B9 -> 12400000 | D5: =C5-B5 -> 600000 | E5: =D5/B5 -> 0.050847458 | F5: =IF(D5>=0,"Favorable","Unfavorable") -> Favorable
A6: COGS | B6: ='05 P&L'!C15 -> 4600000 | C6: ='05 P&L'!B15 -> 4700000 | D6: =B6-C6 -> -100000 | E6: =D6/B6 -> -0.02173913 | F6: =IF(D6>=0,"Favorable","Unfavorable") -> Unfavorable
A7: Salaries | B7: ='05 P&L'!C18 -> 1800000 | C7: ='05 P&L'!B18 -> 1900000 | D7: =B7-C7 -> -100000 | E7: =D7/B7 -> -0.055555556 | F7: =IF(D7>=0,"Favorable","Unfavorable") -> Unfavorable
A8: Marketing | B8: ='05 P&L'!C20 -> 400000 | C8: ='05 P&L'!B20 -> 350000 | D8: =B8-C8 -> 50000 | E8: =D8/B8 -> 0.125 | F8: =IF(D8>=0,"Favorable","Unfavorable") -> Favorable
A9: Total Opex | B9: ='05 P&L'!C27 -> 3570000 | C9: ='05 P&L'!B27 -> 3760000 | D9: =B9-C9 -> -190000 | E9: =D9/B9 -> -0.053221289 | F9: =IF(D9>=0,"Favorable","Unfavorable") -> Unfavorable
A10: EBITDA | B10: ='05 P&L'!C28 -> 3630000 | C10: ='05 P&L'!B28 -> 3940000 | D10: =C10-B10 -> 310000 | E10: =D10/B10 -> 0.085399449 | F10: =IF(D10>=0,"Favorable","Unfavorable") -> Favorable
A11: Net Profit | B11: ='05 P&L'!C32 -> 2550000 | C11: ='05 P&L'!B32 -> 2790000 | D11: =C11-B11 -> 240000 | E11: =D11/B11 -> 0.094117647 | F11: =IF(D11>=0,"Favorable","Unfavorable") -> Favorable

Sheet 09 KPI Analysis
A1: KPI ANALYSIS
A2: Monthly Financial Report | August 2026 | Confidential | H2: ← Dashboard | I2: 🏠 Home | J2: → Variance Analysis
A4: Financial KPI | B4: Current Month
A5: Revenue Growth % | B5: ='14 Monthly Trends'!I5/'14 Monthly Trends'!H5-1 -> 0.024793388
A6: Gross Margin % | B6: ='05 P&L'!B16/'05 P&L'!B9 -> 0.62096774
A7: EBITDA Margin % | B7: ='05 P&L'!B28/'05 P&L'!B9 -> 0.31774194
A8: Net Profit Margin % | B8: ='05 P&L'!B32/'05 P&L'!B9 -> 0.225
A9: Operating Expense % | B9: ='05 P&L'!B27/'05 P&L'!B9 -> 0.30322581
A10: Current Ratio | B10: =('06 Balance Sheet'!B6+'06 Balance Sheet'!B7+'06 Balance Sheet'!B8+'06 Balance Sheet'!B9+'06 Balance Sheet'!B10)/('06 Balance Sheet'!B17+'06 Balance Sheet'!B18+'06 Balance Sheet'!B19+'06 Balance Sheet'!B20) -> 3.0606061
A11: Debt-to-Equity | B11: =('06 Balance Sheet'!B22+'06 Balance Sheet'!B23)/'06 Balance Sheet'!B25 -> 0.46931408
A12: ROE | B12: ='05 P&L'!B32/'06 Balance Sheet'!B25 -> 0.20144404
A13: ROA | B13: ='05 P&L'!B32/'06 Balance Sheet'!B5 -> 0.10689655
A14: DSO – Days Sales Outstanding | B14: 36
A15: DPO – Days Payable Outstanding | B15: 28
A16: Inventory Days | B16: 18
A17: Cash Conversion Cycle | B17: =B14+B16-B15 -> 26

Sheet 10 Variance Analysis
A1: VARIANCE ANALYSIS
A2: Monthly Financial Report | August 2026 | Confidential | H2: ← Dashboard | I2: 🏠 Home | J2: → AR Aging
A4: Account | B4: Budget | C4: Actual | D4: Variance | E4: Variance % | F4: Reason | G4: Action | H4: Owner
A5: Revenue | B5: 11800000 | C5: 12400000 | D5: 600000 | E5: 0.0508 | F5: Higher product & service sales | G5: Maintain sales momentum | H5: Sales
A6: Salaries | B6: 1800000 | C6: 1900000 | D6: -100000 | E6: -0.0556 | F6: New hires | G6: Review staffing plan | H6: HR
A7: Marketing | B7: 400000 | C7: 350000 | D7: 50000 | E7: 0.125 | F7: Campaign timing | G7: Reallocate to high ROI channels | H7: Marketing
A8: COGS | B8: 4600000 | C8: 4700000 | D8: -100000 | E8: -0.0217 | F8: Material cost inflation | G8: Negotiate suppliers | H8: Operations

Sheet 11 AR Aging
A1: 11 AR AGING
A2: Monthly Financial Report | August 2026 | Confidential | H2: ← Dashboard | I2: 🏠 Home | J2: → AP Aging
A4: Customer | B4: Invoice Number | C4: Invoice Date | D4: Due Date | E4: Invoice Amount | F4: Received / Paid | G4: Outstanding | H4: Days Outstanding | I4: Aging Bucket
A5: Orion Retail | B5: INV-1001 | C5: 46204 | D5: 46234 | E5: 800000 | F5: 300000 | G5: =E5-F5 -> 500000 | H5: =MAX(0,DATE(2026,8,31)-D5) -> 31 | I5: =IF(H5=0,"Current",IF(H5<=30,"1–30 Days",IF(H5<=60,"31–60 Days",IF(H5<=90,"61–90 Days","90+ Days")))) -> 31–60 Days
A6: Northstar Ltd | B6: INV-1002 | C6: 46218 | D6: 46248 | E6: 650000 | F6: 0 | G6: =E6-F6 -> 650000 | H6: =MAX(0,DATE(2026,8,31)-D6) -> 17 | I6: =IF(H6=0,"Current",IF(H6<=30,"1–30 Days",IF(H6<=60,"31–60 Days",IF(H6<=90,"61–90 Days","90+ Days")))) -> 1–30 Days
A7: Zenith Corp | B7: INV-1003 | C7: 46172 | D7: 46202 | E7: 1200000 | F7: 0 | G7: =E7-F7 -> 1200000 | H7: =MAX(0,DATE(2026,8,31)-D7) -> 63 | I7: =IF(H7=0,"Current",IF(H7<=30,"1–30 Days",IF(H7<=60,"31–60 Days",IF(H7<=90,"61–90 Days","90+ Days")))) -> 61–90 Days
A10: Aging Summary
A11: Current | B11: =SUMIF(I5:I7,"Current",G5:G7) -> 0
A12: 1–30 Days | B12: =SUMIF(I5:I7,"1–30 Days",G5:G7) -> 650000
A13: 31–60 Days | B13: =SUMIF(I5:I7,"31–60 Days",G5:G7) -> 500000
A14: 61–90 Days | B14: =SUMIF(I5:I7,"61–90 Days",G5:G7) -> 1200000
A15: 90+ Days | B15: =SUMIF(I5:I7,"90+ Days",G5:G7) -> 0

Sheet 12 AP Aging
A1: 12 AP AGING
A2: Monthly Financial Report | August 2026 | Confidential | H2: ← Dashboard | I2: 🏠 Home | J2: → Expense Analysis
A4: Vendor | B4: Invoice Number | C4: Invoice Date | D4: Due Date | E4: Invoice Amount | F4: Received / Paid | G4: Outstanding | H4: Days Outstanding | I4: Aging Bucket
A5: Alpha Supplies | B5: BILL-2001 | C5: 46205 | D5: 46235 | E5: 500000 | F5: 200000 | G5: =E5-F5 -> 300000 | H5: =MAX(0,DATE(2026,8,31)-D5) -> 30 | I5: =IF(H5=0,"Current",IF(H5<=30,"1–30 Days",IF(H5<=60,"31–60 Days",IF(H5<=90,"61–90 Days","90+ Days")))) -> 1–30 Days
A6: Beta Services | B6: BILL-2002 | C6: 46223 | D6: 46253 | E6: 350000 | F6: 0 | G6: =E6-F6 -> 350000 | H6: =MAX(0,DATE(2026,8,31)-D6) -> 12 | I6: =IF(H6=0,"Current",IF(H6<=30,"1–30 Days",IF(H6<=60,"31–60 Days",IF(H6<=90,"61–90 Days","90+ Days")))) -> 1–30 Days
A7: Gamma Works | B7: BILL-2003 | C7: 46162 | D7: 46192 | E7: 750000 | F7: 0 | G7: =E7-F7 -> 750000 | H7: =MAX(0,DATE(2026,8,31)-D7) -> 73 | I7: =IF(H7=0,"Current",IF(H7<=30,"1–30 Days",IF(H7<=60,"31–60 Days",IF(H7<=90,"61–90 Days","90+ Days")))) -> 61–90 Days
A10: Aging Summary
A11: Current | B11: =SUMIF(I5:I7,"Current",G5:G7) -> 0
A12: 1–30 Days | B12: =SUMIF(I5:I7,"1–30 Days",G5:G7) -> 650000
A13: 31–60 Days | B13: =SUMIF(I5:I7,"31–60 Days",G5:G7) -> 0
A14: 61–90 Days | B14: =SUMIF(I5:I7,"61–90 Days",G5:G7) -> 750000
A15: 90+ Days | B15: =SUMIF(I5:I7,"90+ Days",G5:G7) -> 0

Sheet 13 Expense Analysis
A1: EXPENSE ANALYSIS
A2: Monthly Financial Report | August 2026 | Confidential | H2: ← Dashboard | I2: 🏠 Home | J2: → Monthly Trends
A4: Expense | B4: Current Month | C4: Budget | D4: Variance | E4: YTD
A5: Salaries | B5: ='05 P&L'!B18 -> 1900000 | C5: ='05 P&L'!C18 -> 1800000 | D5: =C5-B5 -> -100000 | E5: =B5*8 -> 15200000
A6: Rent | B6: ='05 P&L'!B19 -> 520000 | C6: ='05 P&L'!C19 -> 500000 | D6: =C6-B6 -> -20000 | E6: =B6*8 -> 4160000
A7: Marketing | B7: ='05 P&L'!B20 -> 350000 | C7: ='05 P&L'!C20 -> 400000 | D7: =C7-B7 -> 50000 | E7: =B7*8 -> 2800000
A8: IT | B8: ='05 P&L'!B21 -> 220000 | C8: ='05 P&L'!C21 -> 200000 | D8: =C8-B8 -> -20000 | E8: =B8*8 -> 1760000
A9: Travel | B9: ='05 P&L'!B22 -> 130000 | C9: ='05 P&L'!C22 -> 120000 | D9: =C9-B9 -> -10000 | E9: =B9*8 -> 1040000
A10: Professional Fees | B10: ='05 P&L'!B23 -> 180000 | C10: ='05 P&L'!C23 -> 150000 | D10: =C10-B10 -> -30000 | E10: =B10*8 -> 1440000

Sheet 14 Monthly Trends
A1: MONTHLY TREND ANALYSIS
A2: Monthly Financial Report | August 2026 | Confidential | H2: ← Dashboard | I2: 🏠 Home | J2: → Notes & Commentary
A4: KPI | B4: Jan | C4: Feb | D4: Mar | E4: Apr | F4: May | G4: Jun | H4: Jul | I4: Aug | J4: Sep | K4: Oct | L4: Nov | M4: Dec
A5: Revenue | B5: 10000000 | C5: 10500000 | D5: 11000000 | E5: 11400000 | F5: 12000000 | G5: 12400000 | H5: 12100000 | I5: 12400000 | J5: 12800000 | K5: 13100000 | L5: 13400000 | M5: 13800000
A6: Gross Profit | B6: 6200000 | C6: 6500000 | D6: 6800000 | E6: 7000000 | F6: 7400000 | G6: 7700000 | H6: 7500000 | I6: 7700000 | J6: 8000000 | K6: 8250000 | L6: 8500000 | M6: 8800000
A7: EBITDA | B7: 2000000 | C7: 2100000 | D7: 2200000 | E7: 2300000 | F7: 2500000 | G7: 2800000 | H7: 2600000 | I7: 2800000 | J7: 3000000 | K7: 3150000 | L7: 3300000 | M7: 3500000
A8: Net Profit | B8: 1100000 | C8: 1200000 | D8: 1300000 | E8: 1400000 | F8: 1500000 | G8: 1700000 | H8: 1550000 | I8: 1700000 | J8: 1850000 | K8: 1950000 | L8: 2050000 | M8: 2200000
A9: Cash | B9: 6500000 | C9: 6700000 | D9: 6900000 | E9: 7100000 | F9: 7800000 | G9: 8300000 | H9: 8000000 | I9: 8300000 | J9: 8500000 | K9: 8800000 | L9: 9000000 | M9: 9500000
A10: Operating Expenses | B10: 4200000 | C10: 4400000 | D10: 4600000 | E10: 4700000 | F10: 4900000 | G10: 4900000 | H10: 4900000 | I10: 4900000 | J10: 5000000 | K10: 5100000 | L10: 5200000 | M10: 5300000

Sheet 15 Notes & Commentary
A1: NOTES & MANAGEMENT COMMENTARY
A2: Monthly Financial Report | August 2026 | Confidential | H2: ← Dashboard | I2: 🏠 Home
A4: Key Highlights
A5: Revenue exceeded budget, EBITDA improved and cash remains above plan. Use this area for management’s monthly narrative.
A9: Key Concerns
A10: Document major unfavorable variances, working capital risks, and cash-flow issues.
A14: Management Actions
A15: Record agreed actions, owners, deadlines and progress here.
