Workbook

Sheet Dashboard
A1: Break-Even Calculator | Executive Dashboard
A2: A decision-ready view of break-even, profitability, capacity, cash payback, and scenario risk.
A4: Active Scenario | C4: Business / Product | E4: Model Start | G4: Model Status
A5: =Inputs!$B$5 -> Base Case | C5: =Inputs!$B$6 -> Example Product / Service | E5: =Inputs!$B$7 -> 46023 | G5: =Checks!$B$4 -> PASS
A7: Key Decision Metrics
A8: Break-even Units / Month | D8: Break-even Revenue / Month (INR) | G8: Contribution / Unit (INR) | J8: Average Forecast Profit / Month (INR)
A9: =IF((Inputs!$B$11-Inputs!$B$12)<=0,"N/A",ROUNDUP(Inputs!$B$13/(Inputs!$B$11-Inputs!$B$12),0)) -> 500 | D9: =IF((Inputs!$B$11-Inputs!$B$12)<=0,"N/A",ROUND(Inputs!$B$13/((Inputs!$B$11-Inputs!$B$12)/Inputs!$B$11),0)) -> 500000 | G9: =Inputs!$B$11-Inputs!$B$12 -> 400 | J9: =ROUND(AVERAGE('Monthly Model'!$B$15:$M$15),0) -> 125533
A12: Cash Break-even Month | D12: Capacity at Break-even | G12: Margin of Safety | J12: Viability Status
A13: =IF('Monthly Model'!$M$19<0,"Beyond 12 months",INDEX('Monthly Model'!$B$4:$M$4,1,MATCH(1,'Monthly Model'!$B$20:$M$20,0))) -> 46204 | D13: =IFERROR(A9/Inputs!$B$16,0) -> 0.45454545 | G13: =IFERROR((AVERAGE('Monthly Model'!$B$6:$M$6)-A9)/AVERAGE('Monthly Model'!$B$6:$M$6),0) -> 0.38562359 | J13: =INDEX(Scenarios!$B$26:$D$26,1,MATCH(Inputs!$B$5,Scenarios!$B$4:$D$4,0)) -> PROFITABLE
A16: Break-Even Curve Data
A17: Units sold | B17: Revenue | C17: Total cost | D17: Fixed cost
A18: 0 | B18: =A18*Inputs!$B$11 -> 0 | C18: =Inputs!$B$13+(A18*Inputs!$B$12) -> 200000 | D18: =Inputs!$B$13 -> 200000
A19: 200 | B19: =A19*Inputs!$B$11 -> 200000 | C19: =Inputs!$B$13+(A19*Inputs!$B$12) -> 320000 | D19: =Inputs!$B$13 -> 200000
A20: 400 | B20: =A20*Inputs!$B$11 -> 400000 | C20: =Inputs!$B$13+(A20*Inputs!$B$12) -> 440000 | D20: =Inputs!$B$13 -> 200000
A21: 600 | B21: =A21*Inputs!$B$11 -> 600000 | C21: =Inputs!$B$13+(A21*Inputs!$B$12) -> 560000 | D21: =Inputs!$B$13 -> 200000
A22: 800 | B22: =A22*Inputs!$B$11 -> 800000 | C22: =Inputs!$B$13+(A22*Inputs!$B$12) -> 680000 | D22: =Inputs!$B$13 -> 200000
A23: 1000 | B23: =A23*Inputs!$B$11 -> 1000000 | C23: =Inputs!$B$13+(A23*Inputs!$B$12) -> 800000 | D23: =Inputs!$B$13 -> 200000
A24: 1200 | B24: =A24*Inputs!$B$11 -> 1200000 | C24: =Inputs!$B$13+(A24*Inputs!$B$12) -> 920000 | D24: =Inputs!$B$13 -> 200000
A27: Scenario Comparison
A28: Scenario | B28: Break-even Units | C28: Forecast Profit / Month | D28: Capacity at BE | E28: Viability
A29: Downside | B29: =Scenarios!$B$20 -> 880 | C29: =Scenarios!$B$22 -> -101102 | D29: =Scenarios!$B$24 -> 0.88 | E29: =Scenarios!$B$26 -> BELOW B/E
A30: Base Case | B30: =Scenarios!$C$20 -> 500 | C30: =Scenarios!$C$22 -> 125559 | D30: =Scenarios!$C$24 -> 0.45454545 | E30: =Scenarios!$C$26 -> PROFITABLE
A31: Upside | B31: =Scenarios!$D$20 -> 387 | C31: =Scenarios!$D$22 -> 357405 | D31: =Scenarios!$D$24 -> 0.258 | E31: =Scenarios!$D$26 -> PROFITABLE
A34: Management Recommendation
A35: =IF(J13="PROFITABLE","Base case is profitable. Protect price, variable cost, and sales ramp assumptions; monitor actual performance against the monthly plan.","Action required before approval: improve price, reduce variable cost, increase viable volume, or address the capacity gap.") -> Base case is profitable. Protect price, variable cost, and sales ramp assumptions; monitor actual performance against the monthly plan.
A43: Scenario | B43: Forecast Profit / Month (INR)
A44: Downside | B44: =Scenarios!$B$22 -> -101102
A45: Base Case | B45: =Scenarios!$C$22 -> 125559
A46: Upside | B46: =Scenarios!$D$22 -> 357405

Sheet Inputs
A1: Break-Even Calculator | Model Controls
A2: Choose the active scenario here. Update assumptions in the Scenarios tab; active values below are linked automatically.
A4: Model Controls | D4: Model Legend & User Notes
A5: Selected scenario | B5: Base Case | D5: Blue font + yellow fill | E5: Editable control or scenario assumption
A6: Business / product name | B6: Example Product / Service | D6: Green font | E6: Linked value from another worksheet
A7: Model start month | B7: 46023 | D7: Black font | E7: Calculation or output
A8: Currency | B8: INR (₹) | D8: Red result | E8: Review required / exception
A10: Active Scenario Assumptions | D10: How to use: (1) Select a scenario above. (2) Update the blue-font assumptions in the Scenarios tab with approved figures. (3) Review the Dashboard for the break-even decision, key risks, and capacity impact. All figures are monthly unless stated otherwise.
A11: Net selling price / unit (INR) | B11: =INDEX(Scenarios!$B$5:$D$5,1,MATCH($B$5,Scenarios!$B$4:$D$4,0)) -> 1000
A12: Variable cost / unit (INR) | B12: =INDEX(Scenarios!$B$6:$D$6,1,MATCH($B$5,Scenarios!$B$4:$D$4,0)) -> 600
A13: Fixed operating cost / month (INR) | B13: =INDEX(Scenarios!$B$7:$D$7,1,MATCH($B$5,Scenarios!$B$4:$D$4,0)) -> 200000
A14: Opening monthly unit sales | B14: =INDEX(Scenarios!$B$8:$D$8,1,MATCH($B$5,Scenarios!$B$4:$D$4,0)) -> 650
A15: Monthly sales growth | B15: =INDEX(Scenarios!$B$9:$D$9,1,MATCH($B$5,Scenarios!$B$4:$D$4,0)) -> 0.04
A16: Maximum capacity / month | B16: =INDEX(Scenarios!$B$10:$D$10,1,MATCH($B$5,Scenarios!$B$4:$D$4,0)) -> 1100
A17: Target profit / month (INR) | B17: =INDEX(Scenarios!$B$11:$D$11,1,MATCH($B$5,Scenarios!$B$4:$D$4,0)) -> 100000
A18: Initial investment (INR) | B18: =INDEX(Scenarios!$B$12:$D$12,1,MATCH($B$5,Scenarios!$B$4:$D$4,0)) -> 500000
A19: One-off launch costs (INR) | B19: =INDEX(Scenarios!$B$13:$D$13,1,MATCH($B$5,Scenarios!$B$4:$D$4,0)) -> 150000

Sheet Scenarios
A1: Break-Even Calculator | Scenario Assumptions
A2: Blue-font cells are editable assumptions. Replace illustrative values with client-approved inputs.
A3: Scenario Assumptions | F3: Scenario Governance
A4: Parameter | B4: Downside | C4: Base Case | D4: Upside | F4: Field | G4: Guidance | H4: Owner | I4: Review Status | J4: Notes
A5: Net selling price / unit (INR) | B5: 900 | C5: 1000 | D5: 1100 | F5: Price | G5: Use net realised price after discounts and returns. | H5: Commercial | I5: To validate | J5: Illustrative template
A6: Variable cost / unit (INR) | B6: 650 | C6: 600 | D6: 570 | F6: Variable cost | G6: Include fulfilment, fees, commissions, returns, and direct labour. | H6: Operations | I6: To validate | J6: Illustrative template
A7: Fixed operating cost / month (INR) | B7: 220000 | C7: 200000 | D7: 205000 | F7: Fixed cost | G7: Use recurring monthly operating costs only. | H7: Finance | I7: To validate | J7: Illustrative template
A8: Opening monthly unit sales | B8: 450 | C8: 650 | D8: 800 | F8: Sales volume | G8: Use an achievable ramp, reconciled to the sales plan. | H8: Commercial | I8: To validate | J8: Illustrative template
A9: Monthly sales growth | B9: 0.01 | C9: 0.04 | D9: 0.05 | F9: Capacity | G9: Confirm with production, service delivery, or staffing plan. | H9: Operations | I9: To validate | J9: Illustrative template
A10: Maximum capacity / month | B10: 1000 | C10: 1100 | D10: 1500
A11: Target profit / month (INR) | B11: 50000 | C11: 100000 | D11: 150000
A12: Initial investment (INR) | B12: 550000 | C12: 500000 | D12: 500000
A13: One-off launch costs (INR) | B13: 200000 | C13: 150000 | D13: 150000
A15: Scenario Outputs
A16: Metric | B16: Downside | C16: Base Case | D16: Upside
A17: Contribution / unit (INR) | B17: =B5-B6 -> 250 | C17: =C5-C6 -> 400 | D17: =D5-D6 -> 530
A18: Contribution margin % | B18: =IFERROR(B17/B5,0) -> 0.27777778 | C18: =IFERROR(C17/C5,0) -> 0.4 | D18: =IFERROR(D17/D5,0) -> 0.48181818
A19: Average monthly units (12 months) | B19: =IF(B9=0,B8,B8*(((1+B9)^12-1)/(B9*12))) -> 475.59386 | C19: =IF(C9=0,C8,C8*(((1+C9)^12-1)/(C9*12))) -> 813.8978 | D19: =IF(D9=0,D8,D8*(((1+D9)^12-1)/(D9*12))) -> 1061.1418
A20: Break-even units / month | B20: =IF(B17<=0,"N/A",ROUNDUP(B7/B17,0)) -> 880 | C20: =IF(C17<=0,"N/A",ROUNDUP(C7/C17,0)) -> 500 | D20: =IF(D17<=0,"N/A",ROUNDUP(D7/D17,0)) -> 387
A21: Break-even revenue / month (INR) | B21: =IF(B18<=0,"N/A",ROUND(B7/B18,0)) -> 792000 | C21: =IF(C18<=0,"N/A",ROUND(C7/C18,0)) -> 500000 | D21: =IF(D18<=0,"N/A",ROUND(D7/D18,0)) -> 425472
A22: Forecast profit / month (INR) | B22: =ROUND(B19*B17-B7,0) -> -101102 | C22: =ROUND(C19*C17-C7,0) -> 125559 | D22: =ROUND(D19*D17-D7,0) -> 357405
A23: Margin of safety | B23: =IFERROR((B19-B20)/B19,0) -> -0.85031824 | C23: =IFERROR((C19-C20)/C19,0) -> 0.38567225 | D23: =IFERROR((D19-D20)/D19,0) -> 0.63529849
A24: Capacity use at break-even | B24: =IFERROR(B20/B10,0) -> 0.88 | C24: =IFERROR(C20/C10,0) -> 0.45454545 | D24: =IFERROR(D20/D10,0) -> 0.258
A25: Cash payback (months) | B25: =IF(B22<=0,"N/A",(B12+B13)/B22) -> N/A | C25: =IF(C22<=0,"N/A",(C12+C13)/C22) -> 5.1768491 | D25: =IF(D22<=0,"N/A",(D12+D13)/D22) -> 1.8186651
A26: Viability status | B26: =IF(B17<=0,"NEGATIVE CONTRIBUTION",IF(B20>B10,"CAPACITY GAP",IF(B22>=0,"PROFITABLE","BELOW B/E"))) -> BELOW B/E | C26: =IF(C17<=0,"NEGATIVE CONTRIBUTION",IF(C20>C10,"CAPACITY GAP",IF(C22>=0,"PROFITABLE","BELOW B/E"))) -> PROFITABLE | D26: =IF(D17<=0,"NEGATIVE CONTRIBUTION",IF(D20>D10,"CAPACITY GAP",IF(D22>=0,"PROFITABLE","BELOW B/E"))) -> PROFITABLE

Sheet Monthly Model
A1: Break-Even Calculator | 12-Month Operating Model
A2: Formula-driven monthly ramp using the selected scenario. All values are in INR unless stated otherwise.
A4: Month | B4: =Inputs!$B$7 -> 46023 | C4: =EDATE(B4,1) -> 46054 | D4: =EDATE(C4,1) -> 46082 | E4: =EDATE(D4,1) -> 46113 | F4: =EDATE(E4,1) -> 46143 | G4: =EDATE(F4,1) -> 46174 | H4: =EDATE(G4,1) -> 46204 | I4: =EDATE(H4,1) -> 46235 | J4: =EDATE(I4,1) -> 46266 | ... M4: =EDATE(L4,1) -> 46357
A5: Month number | B5: 1 | C5: 2 | D5: 3 | E5: 4 | F5: 5 | G5: 6 | H5: 7 | I5: 8 | J5: 9 | K5: 10 | L5: 11 | M5: 12
A6: Unit sales | B6: =ROUND(Inputs!$B$14*(1+Inputs!$B$15)^(B$5-1),0) -> 650 | C6: =ROUND(Inputs!$B$14*(1+Inputs!$B$15)^(C$5-1),0) -> 676 | D6: =ROUND(Inputs!$B$14*(1+Inputs!$B$15)^(D$5-1),0) -> 703 | E6: =ROUND(Inputs!$B$14*(1+Inputs!$B$15)^(E$5-1),0) -> 731 | F6: =ROUND(Inputs!$B$14*(1+Inputs!$B$15)^(F$5-1),0) -> 760 | G6: =ROUND(Inputs!$B$14*(1+Inputs!$B$15)^(G$5-1),0) -> 791 | H6: =ROUND(Inputs!$B$14*(1+Inputs!$B$15)^(H$5-1),0) -> 822 | I6: =ROUND(Inputs!$B$14*(1+Inputs!$B$15)^(I$5-1),0) -> 855 | ... M6: =ROUND(Inputs!$B$14*(1+Inputs!$B$15)^(M$5-1),0) -> 1001
A7: Capacity | B7: =Inputs!$B$16 -> 1100 | C7: =Inputs!$B$16 -> 1100 | D7: =Inputs!$B$16 -> 1100 | E7: =Inputs!$B$16 -> 1100 | F7: =Inputs!$B$16 -> 1100 | G7: =Inputs!$B$16 -> 1100 | H7: =Inputs!$B$16 -> 1100 | I7: =Inputs!$B$16 -> 1100 | ... M7: =Inputs!$B$16 -> 1100
A8: Capacity utilisation | B8: =IFERROR(B6/B7,0) -> 0.59090909 | C8: =IFERROR(C6/C7,0) -> 0.61454545 | D8: =IFERROR(D6/D7,0) -> 0.63909091 | E8: =IFERROR(E6/E7,0) -> 0.66454545 | F8: =IFERROR(F6/F7,0) -> 0.69090909 | G8: =IFERROR(G6/G7,0) -> 0.71909091 | H8: =IFERROR(H6/H7,0) -> 0.74727273 | I8: =IFERROR(I6/I7,0) -> 0.77727273 | ... M8: =IFERROR(M6/M7,0) -> 0.91
A9: Net revenue / unit | B9: =Inputs!$B$11 -> 1000 | C9: =Inputs!$B$11 -> 1000 | D9: =Inputs!$B$11 -> 1000 | E9: =Inputs!$B$11 -> 1000 | F9: =Inputs!$B$11 -> 1000 | G9: =Inputs!$B$11 -> 1000 | H9: =Inputs!$B$11 -> 1000 | I9: =Inputs!$B$11 -> 1000 | ... M9: =Inputs!$B$11 -> 1000
A10: Variable cost / unit | B10: =Inputs!$B$12 -> 600 | C10: =Inputs!$B$12 -> 600 | D10: =Inputs!$B$12 -> 600 | E10: =Inputs!$B$12 -> 600 | F10: =Inputs!$B$12 -> 600 | G10: =Inputs!$B$12 -> 600 | H10: =Inputs!$B$12 -> 600 | I10: =Inputs!$B$12 -> 600 | ... M10: =Inputs!$B$12 -> 600
A11: Contribution / unit | B11: =B9-B10 -> 400 | C11: =C9-C10 -> 400 | D11: =D9-D10 -> 400 | E11: =E9-E10 -> 400 | F11: =F9-F10 -> 400 | G11: =G9-G10 -> 400 | H11: =H9-H10 -> 400 | I11: =I9-I10 -> 400 | ... M11: =M9-M10 -> 400
A12: Revenue | B12: =B6*B9 -> 650000 | C12: =C6*C9 -> 676000 | D12: =D6*D9 -> 703000 | E12: =E6*E9 -> 731000 | F12: =F6*F9 -> 760000 | G12: =G6*G9 -> 791000 | H12: =H6*H9 -> 822000 | I12: =I6*I9 -> 855000 | ... M12: =M6*M9 -> 1001000
A13: Variable costs | B13: =B6*B10 -> 390000 | C13: =C6*C10 -> 405600 | D13: =D6*D10 -> 421800 | E13: =E6*E10 -> 438600 | F13: =F6*F10 -> 456000 | G13: =G6*G10 -> 474600 | H13: =H6*H10 -> 493200 | I13: =I6*I10 -> 513000 | ... M13: =M6*M10 -> 600600
A14: Fixed costs | B14: =Inputs!$B$13 -> 200000 | C14: =Inputs!$B$13 -> 200000 | D14: =Inputs!$B$13 -> 200000 | E14: =Inputs!$B$13 -> 200000 | F14: =Inputs!$B$13 -> 200000 | G14: =Inputs!$B$13 -> 200000 | H14: =Inputs!$B$13 -> 200000 | I14: =Inputs!$B$13 -> 200000 | ... M14: =Inputs!$B$13 -> 200000
A15: Operating profit / (loss) | B15: =B12-B13-B14 -> 60000 | C15: =C12-C13-C14 -> 70400 | D15: =D12-D13-D14 -> 81200 | E15: =E12-E13-E14 -> 92400 | F15: =F12-F13-F14 -> 104000 | G15: =G12-G13-G14 -> 116400 | H15: =H12-H13-H14 -> 128800 | I15: =I12-I13-I14 -> 142000 | ... M15: =M12-M13-M14 -> 200400
A16: Initial investment | B16: =IF(B$5=1,Inputs!$B$18,0) -> 500000 | C16: =IF(C$5=1,Inputs!$B$18,0) -> 0 | D16: =IF(D$5=1,Inputs!$B$18,0) -> 0 | E16: =IF(E$5=1,Inputs!$B$18,0) -> 0 | F16: =IF(F$5=1,Inputs!$B$18,0) -> 0 | G16: =IF(G$5=1,Inputs!$B$18,0) -> 0 | H16: =IF(H$5=1,Inputs!$B$18,0) -> 0 | I16: =IF(I$5=1,Inputs!$B$18,0) -> 0 | ... M16: =IF(M$5=1,Inputs!$B$18,0) -> 0
A17: One-off launch costs | B17: =IF(B$5=1,Inputs!$B$19,0) -> 150000 | C17: =IF(C$5=1,Inputs!$B$19,0) -> 0 | D17: =IF(D$5=1,Inputs!$B$19,0) -> 0 | E17: =IF(E$5=1,Inputs!$B$19,0) -> 0 | F17: =IF(F$5=1,Inputs!$B$19,0) -> 0 | G17: =IF(G$5=1,Inputs!$B$19,0) -> 0 | H17: =IF(H$5=1,Inputs!$B$19,0) -> 0 | I17: =IF(I$5=1,Inputs!$B$19,0) -> 0 | ... M17: =IF(M$5=1,Inputs!$B$19,0) -> 0
A18: Net cash flow | B18: =B15-B16-B17 -> -590000 | C18: =C15-C16-C17 -> 70400 | D18: =D15-D16-D17 -> 81200 | E18: =E15-E16-E17 -> 92400 | F18: =F15-F16-F17 -> 104000 | G18: =G15-G16-G17 -> 116400 | H18: =H15-H16-H17 -> 128800 | I18: =I15-I16-I17 -> 142000 | ... M18: =M15-M16-M17 -> 200400
A19: Cumulative cash flow | B19: =B18 -> -590000 | C19: =B19+C18 -> -519600 | D19: =C19+D18 -> -438400 | E19: =D19+E18 -> -346000 | F19: =E19+F18 -> -242000 | G19: =F19+G18 -> -125600 | H19: =G19+H18 -> 3200 | I19: =H19+I18 -> 145200 | J19: =I19+J18 -> 301200 | ... M19: =L19+M18 -> 856400
A20: Cash break-even flag | B20: =IF(B19>=0,1,0) -> 0 | C20: =IF(C19>=0,1,0) -> 0 | D20: =IF(D19>=0,1,0) -> 0 | E20: =IF(E19>=0,1,0) -> 0 | F20: =IF(F19>=0,1,0) -> 0 | G20: =IF(G19>=0,1,0) -> 0 | H20: =IF(H19>=0,1,0) -> 1 | I20: =IF(I19>=0,1,0) -> 1 | ... M20: =IF(M19>=0,1,0) -> 1
A21: Capacity check | B21: =IF(B6<=B7,"PASS","FAIL") -> PASS | C21: =IF(C6<=C7,"PASS","FAIL") -> PASS | D21: =IF(D6<=D7,"PASS","FAIL") -> PASS | E21: =IF(E6<=E7,"PASS","FAIL") -> PASS | F21: =IF(F6<=F7,"PASS","FAIL") -> PASS | G21: =IF(G6<=G7,"PASS","FAIL") -> PASS | H21: =IF(H6<=H7,"PASS","FAIL") -> PASS | I21: =IF(I6<=I7,"PASS","FAIL") -> PASS | ... M21: =IF(M6<=M7,"PASS","FAIL") -> PASS

Sheet Checks
A1: Break-Even Calculator | Model Checks
A2: The model status is PASS only when all structural and decision-critical checks pass.
A4: MODEL STATUS | B4: =IF(COUNTIF(E7:E13,"FAIL")=0,"PASS","REVIEW REQUIRED") -> PASS
A6: Check | B6: Actual | C6: Expected / Limit | D6: Difference | E6: Status | F6: Where to fix / note
A7: Contribution per unit is positive | B7: =Inputs!$B$11-Inputs!$B$12 -> 400 | C7: 0 | D7: =B7-C7 -> 400 | E7: =IF(B7>0,"PASS","FAIL") -> PASS | F7: Update price or variable cost assumptions.
A8: Fixed operating costs are non-negative | B8: =Inputs!$B$13 -> 200000 | C8: 0 | D8: =B8-C8 -> 200000 | E8: =IF(B8>=0,"PASS","FAIL") -> PASS | F8: Validate fixed cost source data.
A9: Capacity covers break-even units | B9: =IF((Inputs!$B$11-Inputs!$B$12)<=0,0,ROUNDUP(Inputs!$B$13/(Inputs!$B$11-Inputs!$B$12),0)) -> 500 | C9: =Inputs!$B$16 -> 1100 | D9: =C9-B9 -> 600 | E9: =IF(B9<=C9,"PASS","FAIL") -> PASS | F9: Increase capacity or improve unit economics.
A10: Monthly peak units do not exceed capacity | B10: =MAX('Monthly Model'!$B$6:$M$6) -> 1001 | C10: =Inputs!$B$16 -> 1100 | D10: =C10-B10 -> 99 | E10: =IF(B10<=C10,"PASS","FAIL") -> PASS | F10: Reconcile sales ramp with operational plan.
A11: Selected scenario is valid | B11: =COUNTIF(Scenarios!$B$4:$D$4,Inputs!$B$5) -> 1 | C11: 1 | D11: =B11-C11 -> 0 | E11: =IF(B11=1,"PASS","FAIL") -> PASS | F11: Choose a listed scenario in Inputs.
A12: All active assumptions are populated | B12: =COUNT(Inputs!$B$11:$B$19) -> 9 | C12: 9 | D12: =B12-C12 -> 0 | E12: =IF(B12=C12,"PASS","FAIL") -> PASS | F12: Complete the Scenario assumptions table.
A13: Opening monthly sales are non-negative | B13: =MIN(Scenarios!$B$8:$D$8) -> 450 | C13: 0 | D13: =B13-C13 -> 450 | E13: =IF(B13>=0,"PASS","FAIL") -> PASS | F13: Validate the sales volume assumption.

Sheet Guide & Sources
A1: Break-Even Calculator | User Guide & Sources
A2: Use this sheet for version control, source tracking, and consistent model use.
A4: How to Use the Calculator | D4: Version Control
A5: Step 1 | B5: Select Downside, Base Case, or Upside in the Inputs tab. | D5: Version | E5: 1
A6: Step 2 | B6: Replace blue-font scenario assumptions with approved data. | D6: Prepared date | E6: 46243
A7: Step 3 | B7: Review break-even, capacity, cash payback, and viability on the Dashboard. | D7: Prepared by | E7: Business Analysis Template
A8: Step 4 | B8: Use the Checks tab before sharing the model or making a decision. | D8: Model owner | E8: Finance / Commercial
D9: Status | E9: Illustrative values — replace before client use
A10: Assumption Source Register
A11: Item | B11: Scenario | C11: Value Type | D11: Unit / Period | E11: Source Type | F11: Source / Reference | G11: Owner | H11: Notes
A12: Net selling price | B12: All | C12: Assumption | D12: INR / unit | E12: Commercial plan | F12: Replace with approved price waterfall | G12: Commercial | H12: Net of discounts, returns, and rebates
A13: Variable cost | B13: All | C13: Assumption | D13: INR / unit | E13: Costing file | F13: Replace with supplier / operational costing | G13: Operations | H13: Include fulfilment, fees, and commissions
A14: Fixed operating cost | B14: All | C14: Assumption | D14: INR / month | E14: Budget | F14: Replace with approved monthly budget | G14: Finance | H14: Exclude one-off launch costs
A15: Sales volume | B15: All | C15: Assumption | D15: Units / month | E15: Sales forecast | F15: Replace with approved demand plan | G15: Commercial | H15: Reconcile with capacity
A16: Capacity | B16: All | C16: Assumption | D16: Units / month | E16: Operations plan | F16: Replace with confirmed capacity plan | G16: Operations | H16: Use practical, not theoretical capacity
A18: Model Conventions
A19: Currency | B19: INR (₹), editable in Inputs for documentation purposes.
A20: Periodicity | B20: Monthly operating model; use one consistent period across all inputs.
A21: Tax treatment | B21: Operating break-even before tax. Add tax only if required for a specific client decision.
A22: Break-even | B22: Fixed operating cost divided by unit contribution; rounded up to whole units.
A23: Cash payback | B23: Initial investment plus launch costs divided by positive forecast operating profit per month.
