Workbook

Sheet 01_Cover
A1: MONTHLY PAYROLL & SALARY CALCULATOR
A3: Secure • Configurable • Client-ready payroll workbook
B6: Company Name | C6: Northstar Services Pvt. Ltd.
B7: Payroll Month | C7: August 2026
B8: Financial Year | C8: FY 2026–27
B9: Prepared By | C9: Payroll Team
B10: Payroll Status | C10: Draft / Review
B11: Last Updated | C11: 46245
B14: CONFIDENTIAL — PAYROLL INFORMATION For authorized internal and client use only.

Sheet 02_Dashboard
A1: PAYROLL SUMMARY DASHBOARD
A3: August 2026 • FY 2026–27 • INR
A5: Total Employees | B5: Gross Payroll | C5: Total Deductions | D5: Net Payroll
A6: =COUNTIF('10_Payroll_Register'!$H$5:$H$9,"Active") -> 5 | B6: =SUM('10_Payroll_Register'!$D$5:$D$9) -> 493730.77 | C6: =SUM('10_Payroll_Register'!$E$5:$E$9) -> 72151.202 | D6: =SUM('10_Payroll_Register'!$F$5:$F$9) -> 421579.57
A7: Employer Cost | B7: Average Salary | C7: Overtime Cost | D7: Total LOP
A8: =SUM('10_Payroll_Register'!$G$5:$G$9) -> 533277.64 | B8: =AVERAGE('10_Payroll_Register'!$F$5:$F$9) -> 84315.913 | C8: =SUM('07_Overtime'!$F$5:$F$9) -> 15230.769 | D8: =SUM('06_Attendance_Leave'!$H$5:$H$9) -> 3
A11: Payroll by department
A12: Department | B12: Headcount | C12: Gross Payroll | D12: Net Payroll | E12: Employer Cost
A13: Sales | B13: =COUNTIF('10_Payroll_Register'!$C$5:$C$9,A13) -> 1 | C13: =SUMIF('10_Payroll_Register'!$C$5:$C$9,A13,'10_Payroll_Register'!$D$5:$D$9) -> 130192.31 | D13: =SUMIF('10_Payroll_Register'!$C$5:$C$9,A13,'10_Payroll_Register'!$F$5:$F$9) -> 115306.25 | E13: =SUMIF('10_Payroll_Register'!$C$5:$C$9,A13,'10_Payroll_Register'!$G$5:$G$9) -> 141623.56
A14: Operations | B14: =COUNTIF('10_Payroll_Register'!$C$5:$C$9,A14) -> 1 | C14: =SUMIF('10_Payroll_Register'!$C$5:$C$9,A14,'10_Payroll_Register'!$D$5:$D$9) -> 107206.73 | D14: =SUMIF('10_Payroll_Register'!$C$5:$C$9,A14,'10_Payroll_Register'!$F$5:$F$9) -> 91602.344 | E14: =SUMIF('10_Payroll_Register'!$C$5:$C$9,A14,'10_Payroll_Register'!$G$5:$G$9) -> 116930.95
A15: Technology | B15: =COUNTIF('10_Payroll_Register'!$C$5:$C$9,A15) -> 1 | C15: =SUMIF('10_Payroll_Register'!$C$5:$C$9,A15,'10_Payroll_Register'!$D$5:$D$9) -> 104350.96 | D15: =SUMIF('10_Payroll_Register'!$C$5:$C$9,A15,'10_Payroll_Register'!$F$5:$F$9) -> 85083.089 | E15: =SUMIF('10_Payroll_Register'!$C$5:$C$9,A15,'10_Payroll_Register'!$G$5:$G$9) -> 113502.37
A16: Finance | B16: =COUNTIF('10_Payroll_Register'!$C$5:$C$9,A16) -> 1 | C16: =SUMIF('10_Payroll_Register'!$C$5:$C$9,A16,'10_Payroll_Register'!$D$5:$D$9) -> 82000 | D16: =SUMIF('10_Payroll_Register'!$C$5:$C$9,A16,'10_Payroll_Register'!$F$5:$F$9) -> 67506.154 | E16: =SUMIF('10_Payroll_Register'!$C$5:$C$9,A16,'10_Payroll_Register'!$G$5:$G$9) -> 87040
A17: HR | B17: =COUNTIF('10_Payroll_Register'!$C$5:$C$9,A17) -> 1 | C17: =SUMIF('10_Payroll_Register'!$C$5:$C$9,A17,'10_Payroll_Register'!$D$5:$D$9) -> 69980.769 | D17: =SUMIF('10_Payroll_Register'!$C$5:$C$9,A17,'10_Payroll_Register'!$F$5:$F$9) -> 62081.731 | E17: =SUMIF('10_Payroll_Register'!$C$5:$C$9,A17,'10_Payroll_Register'!$G$5:$G$9) -> 74180.769

Sheet 03_Control_Settings
A1: CONTROL & SETTINGS
A3: Configurable statutory & calculation rules
A4: Company Name | B4: Northstar Services Pvt. Ltd. | E4: Rule | F4: Applicable? | G4: Rate / Amount | H4: Effective From
A5: Payroll Month | B5: August 2026 | E5: Employee PF | F5: Yes | G5: 0.12 | H5: 46113
A6: Financial Year | B6: FY 2026–27 | E6: Employer PF | F6: Yes | G6: 0.12 | H6: 46113
A7: Currency | B7: INR | E7: Employee ESI | F7: Yes | G7: 0.0075 | H7: 46113
A8: Working Days | B8: 26 | E8: Employer ESI | F8: Yes | G8: 0.0325 | H8: 46113
A9: Standard Working Hours | B9: 8 | E9: Professional Tax | F9: Yes | G9: 200 | H9: 46113
A10: Pay Date | B10: 46265 | E10: TDS | F10: Yes | G10: 0.05 | H10: 46113
A11: Salary Rounding | B11: Nearest Rupee
A14: Method | B14: Selected policy | C14: Notes | D14: Owner
A15: Overtime | B15: Hourly rate × OT multiplier | C15: Set rates in Overtime tab | D15: Payroll
A16: LOP | B16: Gross / Working Days × LOP | C16: Formula-driven | D16: Payroll
A17: Leave | B17: Paid leave included | C17: Unpaid leave flows to LOP | D17: HR

Sheet 04_Employee_Master
A1: EMPLOYEE MASTER
A4: Employee ID | B4: Employee Name | C4: Department | D4: Designation | E4: Joining Date | F4: Employment Type | G4: Location | H4: Payment Ref (Masked) | I4: Basic Salary | J4: HRA | K4: Conveyance | L4: Medical | M4: Special Allowance | N4: Other Allowance | O4: Gross Salary | P4: Annual CTC | Q4: PF Applicable | R4: ESI Applicable | S4: Tax Applicable | T4: Status
A5: NST-001 | B5: Aarav Mehta | C5: Sales | D5: Sales Manager | E5: 45089 | F5: Full-time | G5: Mumbai | H5: •••• 4821 | I5: 60000 | J5: 30000 | K5: 4000 | L5: 2000 | M5: 24000 | N5: 0 | O5: =SUM(I5:N5) -> 120000 | P5: =O5*12 -> 1440000 | Q5: Yes | R5: Yes | S5: Yes | T5: Active
A6: NST-002 | B6: Diya Sharma | C6: Operations | D6: Operations Lead | E6: 44866 | F6: Full-time | G6: Pune | H6: •••• 7516 | I6: 52000 | J6: 26000 | K6: 4000 | L6: 2000 | M6: 18000 | N6: 0 | O6: =SUM(I6:N6) -> 102000 | P6: =O6*12 -> 1224000 | Q6: Yes | R6: Yes | S6: Yes | T6: Active
A7: NST-003 | B7: Kabir Singh | C7: Technology | D7: Software Engineer | E7: 45306 | F7: Full-time | G7: Bengaluru | H7: •••• 1984 | I7: 48000 | J7: 24000 | K7: 4000 | L7: 2000 | M7: 17000 | N7: 0 | O7: =SUM(I7:N7) -> 95000 | P7: =O7*12 -> 1140000 | Q7: Yes | R7: Yes | S7: Yes | T7: Active
A8: NST-004 | B8: Meera Iyer | C8: Finance | D8: Finance Analyst | E8: 45719 | F8: Full-time | G8: Chennai | H8: •••• 6290 | I8: 42000 | J8: 21000 | K8: 4000 | L8: 2000 | M8: 13000 | N8: 0 | O8: =SUM(I8:N8) -> 82000 | P8: =O8*12 -> 984000 | Q8: Yes | R8: No | S8: Yes | T8: Active
A9: NST-005 | B9: Rohan Kapoor | C9: HR | D9: HR Executive | E9: 45910 | F9: Full-time | G9: Delhi | H9: •••• 3075 | I9: 35000 | J9: 17500 | K9: 4000 | L9: 2000 | M9: 9500 | N9: 0 | O9: =SUM(I9:N9) -> 68000 | P9: =O9*12 -> 816000 | Q9: Yes | R9: No | S9: Yes | T9: Active

Sheet 05_Salary_Structure
A1: SALARY STRUCTURE
A4: Employee ID | B4: Employee | C4: Basic | D4: HRA | E4: Conveyance | F4: Medical | G4: Special Allowance | H4: Other Allowance | I4: Gross Monthly | J4: Annual CTC
A5: NST-001 | B5: =VLOOKUP($A5,'04_Employee_Master'!$A$5:$T$9,2,FALSE) -> Aarav Mehta | C5: =VLOOKUP($A5,'04_Employee_Master'!$A$5:$T$9,3,FALSE) -> Sales | D5: =VLOOKUP($A5,'04_Employee_Master'!$A$5:$T$9,4,FALSE) -> Sales Manager | E5: =VLOOKUP($A5,'04_Employee_Master'!$A$5:$T$9,5,FALSE) -> 45089 | F5: =VLOOKUP($A5,'04_Employee_Master'!$A$5:$T$9,6,FALSE) -> Full-time | G5: =VLOOKUP($A5,'04_Employee_Master'!$A$5:$T$9,7,FALSE) -> Mumbai | H5: =VLOOKUP($A5,'04_Employee_Master'!$A$5:$T$9,8,FALSE) -> •••• 4821 | I5: =VLOOKUP($A5,'04_Employee_Master'!$A$5:$T$9,9,FALSE) -> 60000 | J5: =VLOOKUP($A5,'04_Employee_Master'!$A$5:$T$9,10,FALSE) -> 30000
A6: NST-002 | B6: =VLOOKUP($A6,'04_Employee_Master'!$A$5:$T$9,2,FALSE) -> Diya Sharma | C6: =VLOOKUP($A6,'04_Employee_Master'!$A$5:$T$9,3,FALSE) -> Operations | D6: =VLOOKUP($A6,'04_Employee_Master'!$A$5:$T$9,4,FALSE) -> Operations Lead | E6: =VLOOKUP($A6,'04_Employee_Master'!$A$5:$T$9,5,FALSE) -> 44866 | F6: =VLOOKUP($A6,'04_Employee_Master'!$A$5:$T$9,6,FALSE) -> Full-time | G6: =VLOOKUP($A6,'04_Employee_Master'!$A$5:$T$9,7,FALSE) -> Pune | H6: =VLOOKUP($A6,'04_Employee_Master'!$A$5:$T$9,8,FALSE) -> •••• 7516 | I6: =VLOOKUP($A6,'04_Employee_Master'!$A$5:$T$9,9,FALSE) -> 52000 | J6: =VLOOKUP($A6,'04_Employee_Master'!$A$5:$T$9,10,FALSE) -> 26000
A7: NST-003 | B7: =VLOOKUP($A7,'04_Employee_Master'!$A$5:$T$9,2,FALSE) -> Kabir Singh | C7: =VLOOKUP($A7,'04_Employee_Master'!$A$5:$T$9,3,FALSE) -> Technology | D7: =VLOOKUP($A7,'04_Employee_Master'!$A$5:$T$9,4,FALSE) -> Software Engineer | E7: =VLOOKUP($A7,'04_Employee_Master'!$A$5:$T$9,5,FALSE) -> 45306 | F7: =VLOOKUP($A7,'04_Employee_Master'!$A$5:$T$9,6,FALSE) -> Full-time | G7: =VLOOKUP($A7,'04_Employee_Master'!$A$5:$T$9,7,FALSE) -> Bengaluru | H7: =VLOOKUP($A7,'04_Employee_Master'!$A$5:$T$9,8,FALSE) -> •••• 1984 | I7: =VLOOKUP($A7,'04_Employee_Master'!$A$5:$T$9,9,FALSE) -> 48000 | J7: =VLOOKUP($A7,'04_Employee_Master'!$A$5:$T$9,10,FALSE) -> 24000
A8: NST-004 | B8: =VLOOKUP($A8,'04_Employee_Master'!$A$5:$T$9,2,FALSE) -> Meera Iyer | C8: =VLOOKUP($A8,'04_Employee_Master'!$A$5:$T$9,3,FALSE) -> Finance | D8: =VLOOKUP($A8,'04_Employee_Master'!$A$5:$T$9,4,FALSE) -> Finance Analyst | E8: =VLOOKUP($A8,'04_Employee_Master'!$A$5:$T$9,5,FALSE) -> 45719 | F8: =VLOOKUP($A8,'04_Employee_Master'!$A$5:$T$9,6,FALSE) -> Full-time | G8: =VLOOKUP($A8,'04_Employee_Master'!$A$5:$T$9,7,FALSE) -> Chennai | H8: =VLOOKUP($A8,'04_Employee_Master'!$A$5:$T$9,8,FALSE) -> •••• 6290 | I8: =VLOOKUP($A8,'04_Employee_Master'!$A$5:$T$9,9,FALSE) -> 42000 | J8: =VLOOKUP($A8,'04_Employee_Master'!$A$5:$T$9,10,FALSE) -> 21000
A9: NST-005 | B9: =VLOOKUP($A9,'04_Employee_Master'!$A$5:$T$9,2,FALSE) -> Rohan Kapoor | C9: =VLOOKUP($A9,'04_Employee_Master'!$A$5:$T$9,3,FALSE) -> HR | D9: =VLOOKUP($A9,'04_Employee_Master'!$A$5:$T$9,4,FALSE) -> HR Executive | E9: =VLOOKUP($A9,'04_Employee_Master'!$A$5:$T$9,5,FALSE) -> 45910 | F9: =VLOOKUP($A9,'04_Employee_Master'!$A$5:$T$9,6,FALSE) -> Full-time | G9: =VLOOKUP($A9,'04_Employee_Master'!$A$5:$T$9,7,FALSE) -> Delhi | H9: =VLOOKUP($A9,'04_Employee_Master'!$A$5:$T$9,8,FALSE) -> •••• 3075 | I9: =VLOOKUP($A9,'04_Employee_Master'!$A$5:$T$9,9,FALSE) -> 35000 | J9: =VLOOKUP($A9,'04_Employee_Master'!$A$5:$T$9,10,FALSE) -> 17500

Sheet 06_Attendance_Leave
A1: ATTENDANCE & LEAVE
A4: Employee ID | B4: Employee | C4: Working Days | D4: Present | E4: Paid Leave | F4: Unpaid Leave | G4: Absent | H4: LOP Days | I4: Half Days | J4: Holidays | K4: Late Days | L4: OT Hours
A5: NST-001 | B5: Aarav Mehta | C5: 26 | D5: 24 | E5: 2 | F5: 0 | G5: 0 | H5: =F5+G5+(I5*0.5) -> 0 | I5: 0 | J5: 0 | K5: 1 | L5: 6
A6: NST-002 | B6: Diya Sharma | C6: 26 | D6: 25 | E6: 1 | F6: 0 | G6: 0 | H6: =F6+G6+(I6*0.5) -> 0 | I6: 0 | J6: 0 | K6: 0 | L6: 3
A7: NST-003 | B7: Kabir Singh | C7: 26 | D7: 23 | E7: 1 | F7: 2 | G7: 0 | H7: =F7+G7+(I7*0.5) -> 2 | I7: 0 | J7: 0 | K7: 2 | L7: 10
A8: NST-004 | B8: Meera Iyer | C8: 26 | D8: 25 | E8: 0 | F8: 1 | G8: 0 | H8: =F8+G8+(I8*0.5) -> 1 | I8: 0 | J8: 0 | K8: 0 | L8: 0
A9: NST-005 | B9: Rohan Kapoor | C9: 26 | D9: 26 | E9: 0 | F9: 0 | G9: 0 | H9: =F9+G9+(I9*0.5) -> 0 | I9: 0 | J9: 0 | K9: 3 | L9: 2

Sheet 07_Overtime
A1: OVERTIME CALCULATOR
A4: Employee ID | B4: Employee | C4: OT Hours | D4: Hourly Rate | E4: OT Multiplier | F4: OT Amount
A5: NST-001 | B5: =VLOOKUP(A5,'04_Employee_Master'!$A$5:$T$9,2,FALSE) -> Aarav Mehta | C5: =VLOOKUP(A5,'06_Attendance_Leave'!$A$5:$L$9,12,FALSE) -> 6 | D5: =VLOOKUP(A5,'04_Employee_Master'!$A$5:$T$9,15,FALSE)/'03_Control_Settings'!$B$8/'03_Control_Settings'!$B$9 -> 576.92308 | E5: 1.5 | F5: =C5*D5*E5 -> 5192.3077
A6: NST-002 | B6: =VLOOKUP(A6,'04_Employee_Master'!$A$5:$T$9,2,FALSE) -> Diya Sharma | C6: =VLOOKUP(A6,'06_Attendance_Leave'!$A$5:$L$9,12,FALSE) -> 3 | D6: =VLOOKUP(A6,'04_Employee_Master'!$A$5:$T$9,15,FALSE)/'03_Control_Settings'!$B$8/'03_Control_Settings'!$B$9 -> 490.38462 | E6: 1.5 | F6: =C6*D6*E6 -> 2206.7308
A7: NST-003 | B7: =VLOOKUP(A7,'04_Employee_Master'!$A$5:$T$9,2,FALSE) -> Kabir Singh | C7: =VLOOKUP(A7,'06_Attendance_Leave'!$A$5:$L$9,12,FALSE) -> 10 | D7: =VLOOKUP(A7,'04_Employee_Master'!$A$5:$T$9,15,FALSE)/'03_Control_Settings'!$B$8/'03_Control_Settings'!$B$9 -> 456.73077 | E7: 1.5 | F7: =C7*D7*E7 -> 6850.9615
A8: NST-004 | B8: =VLOOKUP(A8,'04_Employee_Master'!$A$5:$T$9,2,FALSE) -> Meera Iyer | C8: =VLOOKUP(A8,'06_Attendance_Leave'!$A$5:$L$9,12,FALSE) -> 0 | D8: =VLOOKUP(A8,'04_Employee_Master'!$A$5:$T$9,15,FALSE)/'03_Control_Settings'!$B$8/'03_Control_Settings'!$B$9 -> 394.23077 | E8: 1.5 | F8: =C8*D8*E8 -> 0
A9: NST-005 | B9: =VLOOKUP(A9,'04_Employee_Master'!$A$5:$T$9,2,FALSE) -> Rohan Kapoor | C9: =VLOOKUP(A9,'06_Attendance_Leave'!$A$5:$L$9,12,FALSE) -> 2 | D9: =VLOOKUP(A9,'04_Employee_Master'!$A$5:$T$9,15,FALSE)/'03_Control_Settings'!$B$8/'03_Control_Settings'!$B$9 -> 326.92308 | E9: 1.5 | F9: =C9*D9*E9 -> 980.76923

Sheet 08_Payroll_Calculator
A1: PAYROLL CALCULATOR
A4: Employee ID | B4: Employee | C4: Department | D4: Basic | E4: HRA | F4: Allowances | G4: Bonus | H4: OT | I4: Gross Earnings | J4: PF | K4: ESI | L4: PT | M4: TDS | N4: Loan / Advance | O4: LOP Deduction | P4: Other Deduction | Q4: Total Deductions | R4: NET SALARY | S4: Employer Cost
A5: NST-001 | B5: =VLOOKUP($A5,'04_Employee_Master'!$A$5:$T$9,2,FALSE) -> Aarav Mehta | C5: =VLOOKUP($A5,'04_Employee_Master'!$A$5:$T$9,3,FALSE) -> Sales | D5: =VLOOKUP($A5,'04_Employee_Master'!$A$5:$T$9,9,FALSE) -> 60000 | E5: =VLOOKUP($A5,'04_Employee_Master'!$A$5:$T$9,10,FALSE) -> 30000 | F5: =VLOOKUP($A5,'04_Employee_Master'!$A$5:$T$9,11,FALSE)+VLOOKUP($A5,'04_Employee_Master'!$A$5:$T$9,12,FALSE)+VLOOKUP($A5,'04_Employee_Master'!$A$5:$T$9,13,FALSE)+VLOOKUP($A5,'04_Employee_Master'!$A$5:$T$9,14,FALSE) -> 30000 | G5: =SUMIF('16_Bonus_Incentive'!$A$5:$A$9,$A5,'16_Bonus_Incentive'!$E$5:$E$9) -> 5000 | H5: =VLOOKUP($A5,'07_Overtime'!$A$5:$F$9,6,FALSE) -> 5192.3077 | I5: =SUM(D5:H5) -> 130192.31 | J5: =IF(VLOOKUP($A5,'04_Employee_Master'!$A$5:$T$9,17,FALSE)="Yes",D5*'03_Control_Settings'!$G$5,0) -> 7200 | K5: =IF(VLOOKUP($A5,'04_Employee_Master'!$A$5:$T$9,18,FALSE)="Yes",I5*'03_Control_Settings'!$G$7,0) -> 976.44231 | L5: ='03_Control_Settings'!$G$9 -> 200 | M5: =IF(VLOOKUP($A5,'04_Employee_Master'!$A$5:$T$9,19,FALSE)="Yes",I5*'03_Control_Settings'!$G$10,0) -> 6509.6154 | N5: =SUMIF('15_Loan_Advance'!$A$5:$A$9,$A5,'15_Loan_Advance'!$D$5:$D$9) -> 0 | O5: =VLOOKUP($A5,'04_Employee_Master'!$A$5:$T$9,15,FALSE)/VLOOKUP($A5,'06_Attendance_Leave'!$A$5:$L$9,3,FALSE)*VLOOKUP($A5,'06_Attendance_Leave'!$A$5:$L$9,8,FALSE) -> 0 | P5: =0 -> 0 | Q5: =SUM(J5:P5) -> 14886.058 | R5: =I5-Q5 -> 115306.25 | S5: =I5+IF(VLOOKUP($A5,'04_Employee_Master'!$A$5:$T$9,17,FALSE)="Yes",D5*'03_Control_Settings'!$G$6,0)+IF(VLOOKUP($A5,'04_Employee_Master'!$A$5:$T$9,18,FALSE)="Yes",I5*'03_Control_Settings'!$G$8,0) -> 141623.56
A6: NST-002 | B6: =VLOOKUP($A6,'04_Employee_Master'!$A$5:$T$9,2,FALSE) -> Diya Sharma | C6: =VLOOKUP($A6,'04_Employee_Master'!$A$5:$T$9,3,FALSE) -> Operations | D6: =VLOOKUP($A6,'04_Employee_Master'!$A$5:$T$9,9,FALSE) -> 52000 | E6: =VLOOKUP($A6,'04_Employee_Master'!$A$5:$T$9,10,FALSE) -> 26000 | F6: =VLOOKUP($A6,'04_Employee_Master'!$A$5:$T$9,11,FALSE)+VLOOKUP($A6,'04_Employee_Master'!$A$5:$T$9,12,FALSE)+VLOOKUP($A6,'04_Employee_Master'!$A$5:$T$9,13,FALSE)+VLOOKUP($A6,'04_Employee_Master'!$A$5:$T$9,14,FALSE) -> 24000 | G6: =SUMIF('16_Bonus_Incentive'!$A$5:$A$9,$A6,'16_Bonus_Incentive'!$E$5:$E$9) -> 3000 | H6: =VLOOKUP($A6,'07_Overtime'!$A$5:$F$9,6,FALSE) -> 2206.7308 | I6: =SUM(D6:H6) -> 107206.73 | J6: =IF(VLOOKUP($A6,'04_Employee_Master'!$A$5:$T$9,17,FALSE)="Yes",D6*'03_Control_Settings'!$G$5,0) -> 6240 | K6: =IF(VLOOKUP($A6,'04_Employee_Master'!$A$5:$T$9,18,FALSE)="Yes",I6*'03_Control_Settings'!$G$7,0) -> 804.05048 | L6: ='03_Control_Settings'!$G$9 -> 200 | M6: =IF(VLOOKUP($A6,'04_Employee_Master'!$A$5:$T$9,19,FALSE)="Yes",I6*'03_Control_Settings'!$G$10,0) -> 5360.3365 | N6: =SUMIF('15_Loan_Advance'!$A$5:$A$9,$A6,'15_Loan_Advance'!$D$5:$D$9) -> 3000 | O6: =VLOOKUP($A6,'04_Employee_Master'!$A$5:$T$9,15,FALSE)/VLOOKUP($A6,'06_Attendance_Leave'!$A$5:$L$9,3,FALSE)*VLOOKUP($A6,'06_Attendance_Leave'!$A$5:$L$9,8,FALSE) -> 0 | P6: =0 -> 0 | Q6: =SUM(J6:P6) -> 15604.387 | R6: =I6-Q6 -> 91602.344 | S6: =I6+IF(VLOOKUP($A6,'04_Employee_Master'!$A$5:$T$9,17,FALSE)="Yes",D6*'03_Control_Settings'!$G$6,0)+IF(VLOOKUP($A6,'04_Employee_Master'!$A$5:$T$9,18,FALSE)="Yes",I6*'03_Control_Settings'!$G$8,0) -> 116930.95
A7: NST-003 | B7: =VLOOKUP($A7,'04_Employee_Master'!$A$5:$T$9,2,FALSE) -> Kabir Singh | C7: =VLOOKUP($A7,'04_Employee_Master'!$A$5:$T$9,3,FALSE) -> Technology | D7: =VLOOKUP($A7,'04_Employee_Master'!$A$5:$T$9,9,FALSE) -> 48000 | E7: =VLOOKUP($A7,'04_Employee_Master'!$A$5:$T$9,10,FALSE) -> 24000 | F7: =VLOOKUP($A7,'04_Employee_Master'!$A$5:$T$9,11,FALSE)+VLOOKUP($A7,'04_Employee_Master'!$A$5:$T$9,12,FALSE)+VLOOKUP($A7,'04_Employee_Master'!$A$5:$T$9,13,FALSE)+VLOOKUP($A7,'04_Employee_Master'!$A$5:$T$9,14,FALSE) -> 23000 | G7: =SUMIF('16_Bonus_Incentive'!$A$5:$A$9,$A7,'16_Bonus_Incentive'!$E$5:$E$9) -> 2500 | H7: =VLOOKUP($A7,'07_Overtime'!$A$5:$F$9,6,FALSE) -> 6850.9615 | I7: =SUM(D7:H7) -> 104350.96 | J7: =IF(VLOOKUP($A7,'04_Employee_Master'!$A$5:$T$9,17,FALSE)="Yes",D7*'03_Control_Settings'!$G$5,0) -> 5760 | K7: =IF(VLOOKUP($A7,'04_Employee_Master'!$A$5:$T$9,18,FALSE)="Yes",I7*'03_Control_Settings'!$G$7,0) -> 782.63221 | L7: ='03_Control_Settings'!$G$9 -> 200 | M7: =IF(VLOOKUP($A7,'04_Employee_Master'!$A$5:$T$9,19,FALSE)="Yes",I7*'03_Control_Settings'!$G$10,0) -> 5217.5481 | N7: =SUMIF('15_Loan_Advance'!$A$5:$A$9,$A7,'15_Loan_Advance'!$D$5:$D$9) -> 0 | O7: =VLOOKUP($A7,'04_Employee_Master'!$A$5:$T$9,15,FALSE)/VLOOKUP($A7,'06_Attendance_Leave'!$A$5:$L$9,3,FALSE)*VLOOKUP($A7,'06_Attendance_Leave'!$A$5:$L$9,8,FALSE) -> 7307.6923 | P7: =0 -> 0 | Q7: =SUM(J7:P7) -> 19267.873 | R7: =I7-Q7 -> 85083.089 | S7: =I7+IF(VLOOKUP($A7,'04_Employee_Master'!$A$5:$T$9,17,FALSE)="Yes",D7*'03_Control_Settings'!$G$6,0)+IF(VLOOKUP($A7,'04_Employee_Master'!$A$5:$T$9,18,FALSE)="Yes",I7*'03_Control_Settings'!$G$8,0) -> 113502.37
A8: NST-004 | B8: =VLOOKUP($A8,'04_Employee_Master'!$A$5:$T$9,2,FALSE) -> Meera Iyer | C8: =VLOOKUP($A8,'04_Employee_Master'!$A$5:$T$9,3,FALSE) -> Finance | D8: =VLOOKUP($A8,'04_Employee_Master'!$A$5:$T$9,9,FALSE) -> 42000 | E8: =VLOOKUP($A8,'04_Employee_Master'!$A$5:$T$9,10,FALSE) -> 21000 | F8: =VLOOKUP($A8,'04_Employee_Master'!$A$5:$T$9,11,FALSE)+VLOOKUP($A8,'04_Employee_Master'!$A$5:$T$9,12,FALSE)+VLOOKUP($A8,'04_Employee_Master'!$A$5:$T$9,13,FALSE)+VLOOKUP($A8,'04_Employee_Master'!$A$5:$T$9,14,FALSE) -> 19000 | G8: =SUMIF('16_Bonus_Incentive'!$A$5:$A$9,$A8,'16_Bonus_Incentive'!$E$5:$E$9) -> 0 | H8: =VLOOKUP($A8,'07_Overtime'!$A$5:$F$9,6,FALSE) -> 0 | I8: =SUM(D8:H8) -> 82000 | J8: =IF(VLOOKUP($A8,'04_Employee_Master'!$A$5:$T$9,17,FALSE)="Yes",D8*'03_Control_Settings'!$G$5,0) -> 5040 | K8: =IF(VLOOKUP($A8,'04_Employee_Master'!$A$5:$T$9,18,FALSE)="Yes",I8*'03_Control_Settings'!$G$7,0) -> 0 | L8: ='03_Control_Settings'!$G$9 -> 200 | M8: =IF(VLOOKUP($A8,'04_Employee_Master'!$A$5:$T$9,19,FALSE)="Yes",I8*'03_Control_Settings'!$G$10,0) -> 4100 | N8: =SUMIF('15_Loan_Advance'!$A$5:$A$9,$A8,'15_Loan_Advance'!$D$5:$D$9) -> 2000 | O8: =VLOOKUP($A8,'04_Employee_Master'!$A$5:$T$9,15,FALSE)/VLOOKUP($A8,'06_Attendance_Leave'!$A$5:$L$9,3,FALSE)*VLOOKUP($A8,'06_Attendance_Leave'!$A$5:$L$9,8,FALSE) -> 3153.8462 | P8: =0 -> 0 | Q8: =SUM(J8:P8) -> 14493.846 | R8: =I8-Q8 -> 67506.154 | S8: =I8+IF(VLOOKUP($A8,'04_Employee_Master'!$A$5:$T$9,17,FALSE)="Yes",D8*'03_Control_Settings'!$G$6,0)+IF(VLOOKUP($A8,'04_Employee_Master'!$A$5:$T$9,18,FALSE)="Yes",I8*'03_Control_Settings'!$G$8,0) -> 87040
A9: NST-005 | B9: =VLOOKUP($A9,'04_Employee_Master'!$A$5:$T$9,2,FALSE) -> Rohan Kapoor | C9: =VLOOKUP($A9,'04_Employee_Master'!$A$5:$T$9,3,FALSE) -> HR | D9: =VLOOKUP($A9,'04_Employee_Master'!$A$5:$T$9,9,FALSE) -> 35000 | E9: =VLOOKUP($A9,'04_Employee_Master'!$A$5:$T$9,10,FALSE) -> 17500 | F9: =VLOOKUP($A9,'04_Employee_Master'!$A$5:$T$9,11,FALSE)+VLOOKUP($A9,'04_Employee_Master'!$A$5:$T$9,12,FALSE)+VLOOKUP($A9,'04_Employee_Master'!$A$5:$T$9,13,FALSE)+VLOOKUP($A9,'04_Employee_Master'!$A$5:$T$9,14,FALSE) -> 15500 | G9: =SUMIF('16_Bonus_Incentive'!$A$5:$A$9,$A9,'16_Bonus_Incentive'!$E$5:$E$9) -> 1000 | H9: =VLOOKUP($A9,'07_Overtime'!$A$5:$F$9,6,FALSE) -> 980.76923 | I9: =SUM(D9:H9) -> 69980.769 | J9: =IF(VLOOKUP($A9,'04_Employee_Master'!$A$5:$T$9,17,FALSE)="Yes",D9*'03_Control_Settings'!$G$5,0) -> 4200 | K9: =IF(VLOOKUP($A9,'04_Employee_Master'!$A$5:$T$9,18,FALSE)="Yes",I9*'03_Control_Settings'!$G$7,0) -> 0 | L9: ='03_Control_Settings'!$G$9 -> 200 | M9: =IF(VLOOKUP($A9,'04_Employee_Master'!$A$5:$T$9,19,FALSE)="Yes",I9*'03_Control_Settings'!$G$10,0) -> 3499.0385 | N9: =SUMIF('15_Loan_Advance'!$A$5:$A$9,$A9,'15_Loan_Advance'!$D$5:$D$9) -> 0 | O9: =VLOOKUP($A9,'04_Employee_Master'!$A$5:$T$9,15,FALSE)/VLOOKUP($A9,'06_Attendance_Leave'!$A$5:$L$9,3,FALSE)*VLOOKUP($A9,'06_Attendance_Leave'!$A$5:$L$9,8,FALSE) -> 0 | P9: =0 -> 0 | Q9: =SUM(J9:P9) -> 7899.0385 | R9: =I9-Q9 -> 62081.731 | S9: =I9+IF(VLOOKUP($A9,'04_Employee_Master'!$A$5:$T$9,17,FALSE)="Yes",D9*'03_Control_Settings'!$G$6,0)+IF(VLOOKUP($A9,'04_Employee_Master'!$A$5:$T$9,18,FALSE)="Yes",I9*'03_Control_Settings'!$G$8,0) -> 74180.769

Sheet 09_Statutory_Tax
A1: STATUTORY / TAX RULES
A4: Rule | B4: Applicable? | C4: Rate / Amount | D4: Effective From | E4: Basis | F4: Notes
A5: Employee PF | B5: Yes | C5: 0.12 | D5: 46113 | E5: Basic | F5: Configurable company rule
A6: Employer PF | B6: Yes | C6: 0.12 | D6: 46113 | E6: Basic | F6: Configurable company rule
A7: Employee ESI | B7: Yes | C7: 0.0075 | D7: 46113 | E7: Gross | F7: Eligibility/company rule
A8: Employer ESI | B8: Yes | C8: 0.0325 | D8: 46113 | E8: Gross | F8: Eligibility/company rule
A9: Professional Tax | B9: Yes | C9: 200 | D9: 46113 | E9: Fixed monthly | F9: State/company rule
A10: TDS | B10: Yes | C10: 0.05 | D10: 46113 | E10: Gross | F10: Tax regime/company rule

Sheet 10_Payroll_Register
A1: MONTHLY PAYROLL REGISTER
A4: Employee ID | B4: Employee | C4: Department | D4: Gross Earnings | E4: Deductions | F4: Net Salary | G4: Employer Cost | H4: Status
A5: ='08_Payroll_Calculator'!A5 -> NST-001 | B5: ='08_Payroll_Calculator'!B5 -> Aarav Mehta | C5: ='08_Payroll_Calculator'!C5 -> Sales | D5: ='08_Payroll_Calculator'!I5 -> 130192.31 | E5: ='08_Payroll_Calculator'!Q5 -> 14886.058 | F5: ='08_Payroll_Calculator'!R5 -> 115306.25 | G5: ='08_Payroll_Calculator'!S5 -> 141623.56 | H5: =VLOOKUP(A5,'04_Employee_Master'!$A$5:$T$9,20,FALSE) -> Active
A6: ='08_Payroll_Calculator'!A6 -> NST-002 | B6: ='08_Payroll_Calculator'!B6 -> Diya Sharma | C6: ='08_Payroll_Calculator'!C6 -> Operations | D6: ='08_Payroll_Calculator'!I6 -> 107206.73 | E6: ='08_Payroll_Calculator'!Q6 -> 15604.387 | F6: ='08_Payroll_Calculator'!R6 -> 91602.344 | G6: ='08_Payroll_Calculator'!S6 -> 116930.95 | H6: =VLOOKUP(A6,'04_Employee_Master'!$A$5:$T$9,20,FALSE) -> Active
A7: ='08_Payroll_Calculator'!A7 -> NST-003 | B7: ='08_Payroll_Calculator'!B7 -> Kabir Singh | C7: ='08_Payroll_Calculator'!C7 -> Technology | D7: ='08_Payroll_Calculator'!I7 -> 104350.96 | E7: ='08_Payroll_Calculator'!Q7 -> 19267.873 | F7: ='08_Payroll_Calculator'!R7 -> 85083.089 | G7: ='08_Payroll_Calculator'!S7 -> 113502.37 | H7: =VLOOKUP(A7,'04_Employee_Master'!$A$5:$T$9,20,FALSE) -> Active
A8: ='08_Payroll_Calculator'!A8 -> NST-004 | B8: ='08_Payroll_Calculator'!B8 -> Meera Iyer | C8: ='08_Payroll_Calculator'!C8 -> Finance | D8: ='08_Payroll_Calculator'!I8 -> 82000 | E8: ='08_Payroll_Calculator'!Q8 -> 14493.846 | F8: ='08_Payroll_Calculator'!R8 -> 67506.154 | G8: ='08_Payroll_Calculator'!S8 -> 87040 | H8: =VLOOKUP(A8,'04_Employee_Master'!$A$5:$T$9,20,FALSE) -> Active
A9: ='08_Payroll_Calculator'!A9 -> NST-005 | B9: ='08_Payroll_Calculator'!B9 -> Rohan Kapoor | C9: ='08_Payroll_Calculator'!C9 -> HR | D9: ='08_Payroll_Calculator'!I9 -> 69980.769 | E9: ='08_Payroll_Calculator'!Q9 -> 7899.0385 | F9: ='08_Payroll_Calculator'!R9 -> 62081.731 | G9: ='08_Payroll_Calculator'!S9 -> 74180.769 | H9: =VLOOKUP(A9,'04_Employee_Master'!$A$5:$T$9,20,FALSE) -> Active

Sheet 11_Salary_Slip
A1: SALARY SLIP GENERATOR
A3: Select Employee ID | B3: NST-001
A5: Employee Name | B5: =VLOOKUP($B$3,'04_Employee_Master'!$A$5:$T$9,2,FALSE) -> Aarav Mehta
A6: Designation | B6: =VLOOKUP($B$3,'04_Employee_Master'!$A$5:$T$9,4,FALSE) -> Sales Manager
A7: Department | B7: =VLOOKUP($B$3,'04_Employee_Master'!$A$5:$T$9,3,FALSE) -> Sales
A8: Pay Period | B8: August 2026
A9: Paid Days | B9: =VLOOKUP($B$3,'06_Attendance_Leave'!$A$5:$L$9,4,FALSE)+VLOOKUP($B$3,'06_Attendance_Leave'!$A$5:$L$9,5,FALSE) -> 26
A10: LOP Days | B10: =VLOOKUP($B$3,'06_Attendance_Leave'!$A$5:$L$9,8,FALSE) -> 0
A12: Deductions
A13: Basic | B13: =INDEX('08_Payroll_Calculator'!$D$5:$D$9,MATCH($B$3,'08_Payroll_Calculator'!$A$5:$A$9,0)) -> 60000 | D13: Employee PF | E13: =INDEX('08_Payroll_Calculator'!$J$5:$J$9,MATCH($B$3,'08_Payroll_Calculator'!$A$5:$A$9,0)) -> 7200
A14: HRA | B14: =INDEX('08_Payroll_Calculator'!$E$5:$E$9,MATCH($B$3,'08_Payroll_Calculator'!$A$5:$A$9,0)) -> 30000 | D14: ESI | E14: =INDEX('08_Payroll_Calculator'!$K$5:$K$9,MATCH($B$3,'08_Payroll_Calculator'!$A$5:$A$9,0)) -> 976.44231
A15: Allowances | B15: =INDEX('08_Payroll_Calculator'!$F$5:$F$9,MATCH($B$3,'08_Payroll_Calculator'!$A$5:$A$9,0)) -> 30000 | D15: Professional Tax | E15: =INDEX('08_Payroll_Calculator'!$L$5:$L$9,MATCH($B$3,'08_Payroll_Calculator'!$A$5:$A$9,0)) -> 200
A16: Bonus | B16: =INDEX('08_Payroll_Calculator'!$G$5:$G$9,MATCH($B$3,'08_Payroll_Calculator'!$A$5:$A$9,0)) -> 5000 | D16: TDS | E16: =INDEX('08_Payroll_Calculator'!$M$5:$M$9,MATCH($B$3,'08_Payroll_Calculator'!$A$5:$A$9,0)) -> 6509.6154
A17: Overtime | B17: =INDEX('08_Payroll_Calculator'!$H$5:$H$9,MATCH($B$3,'08_Payroll_Calculator'!$A$5:$A$9,0)) -> 5192.3077 | D17: Loan / Advance | E17: =INDEX('08_Payroll_Calculator'!$N$5:$N$9,MATCH($B$3,'08_Payroll_Calculator'!$A$5:$A$9,0)) -> 0
A18: Gross Earnings | B18: =INDEX('08_Payroll_Calculator'!$I$5:$I$9,MATCH($B$3,'08_Payroll_Calculator'!$A$5:$A$9,0)) -> 130192.31 | D18: LOP Deduction | E18: =INDEX('08_Payroll_Calculator'!$O$5:$O$9,MATCH($B$3,'08_Payroll_Calculator'!$A$5:$A$9,0)) -> 0
D19: Total Deductions | E19: =INDEX('08_Payroll_Calculator'!$Q$5:$Q$9,MATCH($B$3,'08_Payroll_Calculator'!$A$5:$A$9,0)) -> 14886.058
A21: NET PAY | B21: =INDEX('08_Payroll_Calculator'!$R$5:$R$9,MATCH($B$3,'08_Payroll_Calculator'!$A$5:$A$9,0)) -> 115306.25
A22: Net Pay in Words | B22: Configured amount – verify before release

Sheet 12_Department_Analysis
A1: DEPARTMENT-WISE PAYROLL
A4: Department | B4: Headcount | C4: Gross Payroll | D4: Employer Cost | E4: Average Salary
A5: Sales | B5: =COUNTIF('10_Payroll_Register'!$C$5:$C$9,A5) -> 1 | C5: =SUMIF('10_Payroll_Register'!$C$5:$C$9,A5,'10_Payroll_Register'!$D$5:$D$9) -> 130192.31 | D5: =SUMIF('10_Payroll_Register'!$C$5:$C$9,A5,'10_Payroll_Register'!$G$5:$G$9) -> 141623.56 | E5: =IF(B5=0,0,C5/B5) -> 130192.31
A6: Operations | B6: =COUNTIF('10_Payroll_Register'!$C$5:$C$9,A6) -> 1 | C6: =SUMIF('10_Payroll_Register'!$C$5:$C$9,A6,'10_Payroll_Register'!$D$5:$D$9) -> 107206.73 | D6: =SUMIF('10_Payroll_Register'!$C$5:$C$9,A6,'10_Payroll_Register'!$G$5:$G$9) -> 116930.95 | E6: =IF(B6=0,0,C6/B6) -> 107206.73
A7: Technology | B7: =COUNTIF('10_Payroll_Register'!$C$5:$C$9,A7) -> 1 | C7: =SUMIF('10_Payroll_Register'!$C$5:$C$9,A7,'10_Payroll_Register'!$D$5:$D$9) -> 104350.96 | D7: =SUMIF('10_Payroll_Register'!$C$5:$C$9,A7,'10_Payroll_Register'!$G$5:$G$9) -> 113502.37 | E7: =IF(B7=0,0,C7/B7) -> 104350.96
A8: Finance | B8: =COUNTIF('10_Payroll_Register'!$C$5:$C$9,A8) -> 1 | C8: =SUMIF('10_Payroll_Register'!$C$5:$C$9,A8,'10_Payroll_Register'!$D$5:$D$9) -> 82000 | D8: =SUMIF('10_Payroll_Register'!$C$5:$C$9,A8,'10_Payroll_Register'!$G$5:$G$9) -> 87040 | E8: =IF(B8=0,0,C8/B8) -> 82000
A9: HR | B9: =COUNTIF('10_Payroll_Register'!$C$5:$C$9,A9) -> 1 | C9: =SUMIF('10_Payroll_Register'!$C$5:$C$9,A9,'10_Payroll_Register'!$D$5:$D$9) -> 69980.769 | D9: =SUMIF('10_Payroll_Register'!$C$5:$C$9,A9,'10_Payroll_Register'!$G$5:$G$9) -> 74180.769 | E9: =IF(B9=0,0,C9/B9) -> 69980.769

Sheet 13_Payroll_Variance
A1: PAYROLL VARIANCE
A4: Metric | B4: Previous Month | C4: Current Month | D4: Change | E4: Change %
A5: Headcount | B5: 5 | C5: ='02_Dashboard'!A6 -> 5 | D5: =C5-B5 -> 0 | E5: =IF(B5=0,0,D5/B5) -> 0
A6: Gross Payroll | B6: 340000 | C6: ='02_Dashboard'!B6 -> 493730.77 | D6: =C6-B6 -> 153730.77 | E6: =IF(B6=0,0,D6/B6) -> 0.45214932
A7: Net Payroll | B7: 290000 | C7: ='02_Dashboard'!D6 -> 421579.57 | D7: =C7-B7 -> 131579.57 | E7: =IF(B7=0,0,D7/B7) -> 0.45372265
A8: OT Cost | B8: 9000 | C8: ='02_Dashboard'!C8 -> 15230.769 | D8: =C8-B8 -> 6230.7692 | E8: =IF(B8=0,0,D8/B8) -> 0.69230769

Sheet 14_Employee_Cost
A1: EMPLOYEE COST ANALYSIS
A4: Employee ID | B4: Employee | C4: Gross Salary | D4: Employer PF | E4: Employer ESI | F4: Total Employer Cost
A5: NST-001 | B5: =VLOOKUP(A5,'10_Payroll_Register'!$A$5:$H$9,2,FALSE) -> Aarav Mehta | C5: =VLOOKUP(A5,'10_Payroll_Register'!$A$5:$H$9,4,FALSE) -> 130192.31 | D5: =VLOOKUP(A5,'08_Payroll_Calculator'!$A$5:$S$9,4,FALSE)*'03_Control_Settings'!$G$6 -> 7200 | E5: =VLOOKUP(A5,'08_Payroll_Calculator'!$A$5:$S$9,9,FALSE)*'03_Control_Settings'!$G$8 -> 4231.25 | F5: =SUM(C5:E5) -> 141623.56
A6: NST-002 | B6: =VLOOKUP(A6,'10_Payroll_Register'!$A$5:$H$9,2,FALSE) -> Diya Sharma | C6: =VLOOKUP(A6,'10_Payroll_Register'!$A$5:$H$9,4,FALSE) -> 107206.73 | D6: =VLOOKUP(A6,'08_Payroll_Calculator'!$A$5:$S$9,4,FALSE)*'03_Control_Settings'!$G$6 -> 6240 | E6: =VLOOKUP(A6,'08_Payroll_Calculator'!$A$5:$S$9,9,FALSE)*'03_Control_Settings'!$G$8 -> 3484.2188 | F6: =SUM(C6:E6) -> 116930.95
A7: NST-003 | B7: =VLOOKUP(A7,'10_Payroll_Register'!$A$5:$H$9,2,FALSE) -> Kabir Singh | C7: =VLOOKUP(A7,'10_Payroll_Register'!$A$5:$H$9,4,FALSE) -> 104350.96 | D7: =VLOOKUP(A7,'08_Payroll_Calculator'!$A$5:$S$9,4,FALSE)*'03_Control_Settings'!$G$6 -> 5760 | E7: =VLOOKUP(A7,'08_Payroll_Calculator'!$A$5:$S$9,9,FALSE)*'03_Control_Settings'!$G$8 -> 3391.4062 | F7: =SUM(C7:E7) -> 113502.37
A8: NST-004 | B8: =VLOOKUP(A8,'10_Payroll_Register'!$A$5:$H$9,2,FALSE) -> Meera Iyer | C8: =VLOOKUP(A8,'10_Payroll_Register'!$A$5:$H$9,4,FALSE) -> 82000 | D8: =VLOOKUP(A8,'08_Payroll_Calculator'!$A$5:$S$9,4,FALSE)*'03_Control_Settings'!$G$6 -> 5040 | E8: =VLOOKUP(A8,'08_Payroll_Calculator'!$A$5:$S$9,9,FALSE)*'03_Control_Settings'!$G$8 -> 2665 | F8: =SUM(C8:E8) -> 89705
A9: NST-005 | B9: =VLOOKUP(A9,'10_Payroll_Register'!$A$5:$H$9,2,FALSE) -> Rohan Kapoor | C9: =VLOOKUP(A9,'10_Payroll_Register'!$A$5:$H$9,4,FALSE) -> 69980.769 | D9: =VLOOKUP(A9,'08_Payroll_Calculator'!$A$5:$S$9,4,FALSE)*'03_Control_Settings'!$G$6 -> 4200 | E9: =VLOOKUP(A9,'08_Payroll_Calculator'!$A$5:$S$9,9,FALSE)*'03_Control_Settings'!$G$8 -> 2274.375 | F9: =SUM(C9:E9) -> 76455.144

Sheet 15_Loan_Advance
A1: LOAN / ADVANCE TRACKER
A4: Employee ID | B4: Employee | C4: Opening Balance | D4: Monthly Deduction | E4: Closing Balance | F4: Status
A5: NST-001 | B5: Aarav Mehta | C5: 0 | D5: 0 | E5: =MAX(0,C5-D5) -> 0 | F5: Active
A6: NST-002 | B6: Diya Sharma | C6: 15000 | D6: 3000 | E6: =MAX(0,C6-D6) -> 12000 | F6: Active
A7: NST-003 | B7: Kabir Singh | C7: 0 | D7: 0 | E7: =MAX(0,C7-D7) -> 0 | F7: Active
A8: NST-004 | B8: Meera Iyer | C8: 6000 | D8: 2000 | E8: =MAX(0,C8-D8) -> 4000 | F8: Active
A9: NST-005 | B9: Rohan Kapoor | C9: 0 | D9: 0 | E9: =MAX(0,C9-D9) -> 0 | F9: Active

Sheet 16_Bonus_Incentive
A1: BONUS & INCENTIVE TRACKER
A4: Employee ID | B4: Employee | C4: Bonus Type | D4: Target / Achievement | E4: Bonus Amount | F4: Approval
A5: NST-001 | B5: Aarav Mehta | C5: Sales incentive | D5: 105% | E5: 5000 | F5: Approved
A6: NST-002 | B6: Diya Sharma | C6: Performance bonus | D6: 100% | E6: 3000 | F6: Approved
A7: NST-003 | B7: Kabir Singh | C7: Spot award | D7: N/A | E7: 2500 | F7: Approved
A8: NST-004 | B8: Meera Iyer | C8: Performance bonus | D8: N/A | E8: 0 | F8: Pending
A9: NST-005 | B9: Rohan Kapoor | C9: Performance bonus | D9: N/A | E9: 1000 | F9: Approved

Sheet 17_Full_Final
A1: RESIGNATION / FULL & FINAL
A4: Employee ID | B4: Employee | C4: Last Working Date | D4: Salary Due | E4: Leave Encashment | F4: Bonus Due | G4: Notice Pay | H4: Loan Recovery | I4: Final Payable
D5: 0 | E5: 0 | F5: 0 | G5: 0 | H5: 0 | I5: =SUM(D5:F5)-SUM(G5:H5) -> 0

Sheet 18_Reconciliation
A1: RECONCILIATION CHECKS
A4: Check | B4: Actual | C4: Expected | D4: Difference | E4: Status | F4: Notes
A5: Employee Master Count | B5: =COUNTIF('04_Employee_Master'!$T$5:$T$9,"Active") -> 5 | C5: =COUNTA('08_Payroll_Calculator'!$A$5:$A$9) -> 5 | D5: =B5-C5 -> 0 | E5: =IF(ABS(D5)<0.01,"PASS","ERROR") -> PASS | F5: Active employees must match payroll rows
A6: Gross Salary = Components | B6: =SUM('08_Payroll_Calculator'!$I$5:$I$9) -> 493730.77 | C6: =SUM('08_Payroll_Calculator'!$D$5:$D$9)+SUM('08_Payroll_Calculator'!$E$5:$E$9)+SUM('08_Payroll_Calculator'!$F$5:$F$9)+SUM('08_Payroll_Calculator'!$G$5:$G$9)+SUM('08_Payroll_Calculator'!$H$5:$H$9) -> 493730.77 | D6: =B6-C6 -> 0 | E6: =IF(ABS(D6)<0.01,"PASS","ERROR") -> PASS | F6: Payroll gross ties to earnings components
A7: Net Salary = Gross - Deductions | B7: =SUM('08_Payroll_Calculator'!$R$5:$R$9) -> 421579.57 | C7: =SUM('08_Payroll_Calculator'!$I$5:$I$9)-SUM('08_Payroll_Calculator'!$Q$5:$Q$9) -> 421579.57 | D7: =B7-C7 -> 0 | E7: =IF(ABS(D7)<0.01,"PASS","ERROR") -> PASS | F7: Net must reconcile
A8: Department Total = Payroll Total | B8: =SUM('12_Department_Analysis'!$C$5:$C$9) -> 493730.77 | C8: =SUM('10_Payroll_Register'!$D$5:$D$9) -> 493730.77 | D8: =B8-C8 -> 0 | E8: =IF(ABS(D8)<0.01,"PASS","ERROR") -> PASS | F8: Department roll-up ties
A9: Bank Payment = Net Salary | B9: =SUM('10_Payroll_Register'!$F$5:$F$9) -> 421579.57 | C9: =SUM('10_Payroll_Register'!$F$5:$F$9) -> 421579.57 | D9: =B9-C9 -> 0 | E9: =IF(ABS(D9)<0.01,"PASS","ERROR") -> PASS | F9: Payment file to be confirmed

Sheet 19_Notes
A1: MODEL NOTES & USE GUIDE
A4: How to use this workbook 1. Update company settings and statutory rates in Control Settings. 2. Add or amend employees in Employee Master and salary components. 3. Enter monthly attendance, loans and bonuses. 4. Review Payroll Calculator, reconciliation checks and register. 5. Select an employee on Salary Slip before sharing. Colors: Yellow/blue text = user input • Blue fill = calculation • Green = final output • Red should be used for exceptions. Statutory rates are intentionally configurable. Confirm eligibility, caps, thresholds and jurisdictional rules with the appropriate payroll/tax adviser before payment.
