Workbook

Sheet 01_START_HERE
A1: BUSINESS CASH FLOW CONTROL SYSTEM | B1: BUSINESS CASH FLOW CONTROL SYSTEM | C1: BUSINESS CASH FLOW CONTROL SYSTEM | D1: BUSINESS CASH FLOW CONTROL SYSTEM | E1: BUSINESS CASH FLOW CONTROL SYSTEM | F1: BUSINESS CASH FLOW CONTROL SYSTEM | G1: BUSINESS CASH FLOW CONTROL SYSTEM | H1: BUSINESS CASH FLOW CONTROL SYSTEM
A2: Track → Forecast → Control → Grow
A4: WELCOME | B4: WELCOME | C4: WELCOME | D4: WELCOME | E4: WELCOME | F4: WELCOME | G4: WELCOME | H4: WELCOME
A5: This system gives small-business owners a reliable view of current cash, receivables, payables, risks and the next 90 days. Use the highlighted input cells only; every dashboard figure flows from the underlying data.
A8: GET STARTED | B8: GET STARTED | C8: GET STARTED | D8: GET STARTED | F8: BUSINESS SETUP | G8: BUSINESS SETUP | H8: BUSINESS SETUP
A9: 1 | B9: Enter business details below | F9: Business Name | G9: ABC Digital Agency
A10: 2 | B10: Set opening cash balance and safety threshold | F10: Financial Year | G10: 2026–27
A11: 3 | B11: Review accounts and categories in SETTINGS | F11: Currency | G11: ₹
A12: 4 | B12: Add actual cash movements in TRANSACTIONS | F12: Opening Cash Balance | G12: 850000
A13: 5 | B13: Add invoices due in RECEIVABLES and PAYABLES | F13: Forecast Period | G13: 90 Days
A14: 6 | B14: Maintain recurring contracts and subscriptions
A15: 7 | B15: Review Dashboard and Forecast weekly
A17: HOW TO USE THIS WORKBOOK | B17: HOW TO USE THIS WORKBOOK | C17: HOW TO USE THIS WORKBOOK | D17: HOW TO USE THIS WORKBOOK | E17: HOW TO USE THIS WORKBOOK | F17: HOW TO USE THIS WORKBOOK | G17: HOW TO USE THIS WORKBOOK | H17: HOW TO USE THIS WORKBOOK
A18: Profit is not cash. Record money actually received or paid in TRANSACTIONS. Record expected invoices and bills separately. The Forecast combines recurring commitments, expected customer receipts and supplier payments so that you can act before cash gets tight.

Sheet 02_DASHBOARD
A1: BUSINESS CASH FLOW | L1: ="Selected Period: "&TEXT('09_SETTINGS'!$I$8,"dd mmm yyyy") -> Selected Period: 31 Aug 2026 | O1: ='01_START_HERE'!$G$9 -> ABC Digital Agency | T1: Month | U1: Inflow | V1: Outflow | W1: Closing Cash
A2: Cash Flow Control Center | T2: Aug | U2: 240000 | V2: 195000 | W2: 530000
T3: Sep | U3: 155000 | V3: 184200 | W3: 500800
T4: Oct | U4: 155000 | V4: 184200 | W4: 471600
A5: NAVIGATION | C5: CURRENT CASH | D5: CURRENT CASH | E5: CURRENT CASH | F5: CURRENT CASH | G5: TOTAL INFLOW | H5: TOTAL INFLOW | I5: TOTAL INFLOW | J5: TOTAL INFLOW | K5: TOTAL OUTFLOW | L5: TOTAL OUTFLOW | M5: TOTAL OUTFLOW | N5: TOTAL OUTFLOW | O5: NET CASH FLOW | P5: NET CASH FLOW | Q5: NET CASH FLOW
C6: ='01_START_HERE'!$G$12+SUMIFS('03_TRANSACTIONS'!$I$4:$I$203,'03_TRANSACTIONS'!$C$4:$C$203,"Inflow",'03_TRANSACTIONS'!$B$4:$B$203,"<="&'09_SETTINGS'!$I$8)-SUMIFS('03_TRANSACTIONS'!$I$4:$I$203,'03_TRANSACTIONS'!$C$4:$C$203,"Outflow",'03_TRANSACTIONS'!$B$4:$B$203,"<="&'09_SETTINGS'!$I$8) -> 1440000 | G6: ='08_ANALYSIS'!$B$4 -> 240000 | K6: ='08_ANALYSIS'!$B$5 -> 125400 | O6: ='08_ANALYSIS'!$B$6 -> 114600 | T6: Expense Category | U6: Amount
A7: HOME | T7: Salary | U7: 75000
C8: =IF('08_ANALYSIS'!$D$6>=0,"▲ Cash flow improved vs prior month","▼ Cash flow weakened vs prior month") -> ▲ Cash flow improved vs prior month | G8: =IF('08_ANALYSIS'!$D$4>=0,"▲ Higher than prior month","▼ Lower than prior month") -> ▲ Higher than prior month | K8: =IF('08_ANALYSIS'!$D$5>=0,"▲ Higher than prior month","▼ Lower than prior month") -> ▲ Higher than prior month | O8: =IF('08_ANALYSIS'!$B$6>=0,"▲ Healthy positive flow","▼ Negative cash flow") -> ▲ Healthy positive flow | T8: Rent | U8: 25000
T9: Marketing | U9: 18000
A10: DASHBOARD | C10: RECEIVABLES | D10: RECEIVABLES | E10: RECEIVABLES | F10: RECEIVABLES | G10: PAYABLES | H10: PAYABLES | I10: PAYABLES | J10: PAYABLES | K10: OVERDUE AMOUNT | L10: OVERDUE AMOUNT | M10: OVERDUE AMOUNT | N10: OVERDUE AMOUNT | O10: CASH RUNWAY | P10: CASH RUNWAY | Q10: CASH RUNWAY | T10: Software | U10: 4200
C11: =SUM('04_RECEIVABLES'!$G$4:$G$203) -> 365000 | G11: =SUM('05_PAYABLES'!$F$4:$F$203) -> 129200 | K11: =SUMIFS('04_RECEIVABLES'!$G$4:$G$203,'04_RECEIVABLES'!$I$4:$I$203,">0") -> 245000 | O11: ='07_FORECAST'!$B$14 -> 11.483254
T12: Ageing Band | U12: Outstanding
A13: TRANSACTIONS | C13: =IF(SUMIFS('04_RECEIVABLES'!$G$4:$G$203,'04_RECEIVABLES'!$I$4:$I$203,">0")>0,"Collection action required","No overdue balance") -> Collection action required | G13: =IF(SUM('05_PAYABLES'!$F$4:$F$203)>0,"Review upcoming commitments","No unpaid commitments") -> Review upcoming commitments | K13: =IF(K11>0,"Priority: collect overdue invoices","No overdue collections") -> Priority: collect overdue invoices | O13: =IF(O11<3,"Warning: runway below 3 months","Healthy cash cover") -> Healthy cash cover | T13: Current / Due Soon | U13: 195000
T14: 1–30 Days | U14: 0
C15: 90-DAY CASH POSITION | J15: EXPENSE DRIVERS — CURRENT MONTH | T15: 31–60 Days | U15: 0
A16: RECEIVABLES
T17: Year | U17: Cash Inflow | V17: Cash Outflow | W17: Net Cash Flow
T18: 2024 | U18: 255000 | V18: 86800 | W18: 168200
A19: PAYABLES | T19: 2025 | U19: 447000 | V19: 207800 | W19: 239200
T20: 2026 YTD | U20: 500000 | V20: 293400 | W20: 206600
A22: RECURRING
A25: FORECAST
A28: ANALYSIS
C29: RECEIVABLES AGEING | J29: MULTI-YEAR CASH FLOW TREND
A33: Inputs are highlighted on data sheets. Review this dashboard weekly.
C45: MANAGEMENT ACTIONS
C47: 1 | D47: =IF(SUMIFS('04_RECEIVABLES'!$G$4:$G$203,'04_RECEIVABLES'!$I$4:$I$203,">0")>0,"Collect overdue receivables before discretionary spending.","No overdue customer collections require intervention.") -> Collect overdue receivables before discretionary spending.
C48: 2 | D48: Protect high-priority payments: rent, salaries, taxes and essential suppliers.
C49: 3 | D49: =IF('07_FORECAST'!$B$12<'07_FORECAST'!$B$11,"Projected cash drops below the safety threshold — reduce or defer non-essential spend.","Projected cash remains above the safety threshold.") -> Projected cash remains above the safety threshold.
C50: 4 | D50: =IF('08_ANALYSIS'!$D$5>'09_SETTINGS'!$I$6,"Review expense categories with material month-on-month growth.","No material expense growth alert this month.") -> No material expense growth alert this month.

Sheet 03_TRANSACTIONS
A1: TRANSACTIONS — ACTUAL CASH MOVEMENT | B1: TRANSACTIONS — ACTUAL CASH MOVEMENT | C1: TRANSACTIONS — ACTUAL CASH MOVEMENT | D1: TRANSACTIONS — ACTUAL CASH MOVEMENT | E1: TRANSACTIONS — ACTUAL CASH MOVEMENT | F1: TRANSACTIONS — ACTUAL CASH MOVEMENT | G1: TRANSACTIONS — ACTUAL CASH MOVEMENT | H1: TRANSACTIONS — ACTUAL CASH MOVEMENT | I1: TRANSACTIONS — ACTUAL CASH MOVEMENT | J1: TRANSACTIONS — ACTUAL CASH MOVEMENT | K1: TRANSACTIONS — ACTUAL CASH MOVEMENT | L1: TRANSACTIONS — ACTUAL CASH MOVEMENT | M1: TRANSACTIONS — ACTUAL CASH MOVEMENT
A3: Transaction ID | B3: Date | C3: Type | D3: Category | E3: Subcategory | F3: Description | G3: Account | H3: Customer / Vendor | I3: Amount | J3: Status | K3: Payment Method | L3: Notes | M3: Month
A4: TXN-001 | B4: 46236 | C4: Inflow | D4: Services | E4: Retainer | F4: Acme Consulting — Aug | G4: Main Bank | H4: Acme Consulting | I4: 120000 | J4: Received | K4: Bank Transfer | L4: Monthly retainer | M4: =IF(B4="","",TEXT(B4,"mmm-yy")) -> Aug-26
A5: TXN-002 | B5: 46237 | C5: Outflow | D5: Salary | E5: Team | F5: Payroll | G5: Main Bank | H5: Team | I5: 75000 | J5: Paid | K5: Bank Transfer | L5: August payroll | M5: =IF(B5="","",TEXT(B5,"mmm-yy")) -> Aug-26
A6: TXN-003 | B6: 46239 | C6: Outflow | D6: Software | E6: Design | F6: Canva + tools | G6: Main Bank | H6: Canva | I6: 4200 | J6: Paid | K6: Card | M6: =IF(B6="","",TEXT(B6,"mmm-yy")) -> Aug-26
A7: TXN-004 | B7: 46242 | C7: Inflow | D7: Sales | E7: Project | F7: Website project milestone | G7: UPI | H7: Bright Labs | I7: 85000 | J7: Received | K7: UPI | M7: =IF(B7="","",TEXT(B7,"mmm-yy")) -> Aug-26
A8: TXN-005 | B8: 46243 | C8: Outflow | D8: Marketing | E8: Ads | F8: Meta campaigns | G8: Main Bank | H8: Meta | I8: 18000 | J8: Paid | K8: Card | M8: =IF(B8="","",TEXT(B8,"mmm-yy")) -> Aug-26
A9: TXN-006 | B9: 46244 | C9: Outflow | D9: Rent | E9: Office | F9: Studio rent | G9: Main Bank | H9: Office Owner | I9: 25000 | J9: Paid | K9: Bank Transfer | M9: =IF(B9="","",TEXT(B9,"mmm-yy")) -> Aug-26
A10: TXN-007 | B10: 46246 | C10: Inflow | D10: Services | E10: Consulting | F10: Strategy workshop | G10: Main Bank | H10: Nexa Foods | I10: 35000 | J10: Received | K10: Bank Transfer | M10: =IF(B10="","",TEXT(B10,"mmm-yy")) -> Aug-26
A11: TXN-008 | B11: 46249 | C11: Outflow | D11: Utilities | E11: Internet | F11: Internet & mobile | G11: UPI | H11: Airtel | I11: 3200 | J11: Paid | K11: UPI | M11: =IF(B11="","",TEXT(B11,"mmm-yy")) -> Aug-26
A12: TXN-009 | B12: 46206 | C12: Inflow | D12: Services | E12: Retainer | F12: Acme Consulting — Jul | G12: Main Bank | H12: Acme Consulting | I12: 115000 | J12: Received | K12: Bank Transfer | M12: =IF(B12="","",TEXT(B12,"mmm-yy")) -> Jul-26
A13: TXN-010 | B13: 46208 | C13: Outflow | D13: Salary | E13: Team | F13: Payroll | G13: Main Bank | H13: Team | I13: 72000 | J13: Paid | K13: Bank Transfer | M13: =IF(B13="","",TEXT(B13,"mmm-yy")) -> Jul-26
A14: TXN-011 | B14: 46211 | C14: Outflow | D14: Marketing | E14: Ads | F14: Meta campaigns | G14: Main Bank | H14: Meta | I14: 12000 | J14: Paid | K14: Card | M14: =IF(B14="","",TEXT(B14,"mmm-yy")) -> Jul-26
A15: TXN-012 | B15: 46213 | C15: Outflow | D15: Rent | E15: Office | F15: Studio rent | G15: Main Bank | H15: Office Owner | I15: 25000 | J15: Paid | K15: Bank Transfer | M15: =IF(B15="","",TEXT(B15,"mmm-yy")) -> Jul-26
A16: TXN-013 | B16: 45296 | C16: Inflow | D16: Services | E16: Retainer | F16: Acme Consulting — Jan | G16: Main Bank | H16: Acme Consulting | I16: 85000 | J16: Received | K16: Bank Transfer | L16: Historical demo | M16: =IF(B16="","",TEXT(B16,"mmm-yy")) -> Jan-24
A17: TXN-014 | B17: 45299 | C17: Outflow | D17: Salary | E17: Team | F17: Payroll | G17: Main Bank | H17: Team | I17: 48000 | J17: Paid | K17: Bank Transfer | L17: Historical demo | M17: =IF(B17="","",TEXT(B17,"mmm-yy")) -> Jan-24
A18: TXN-015 | B18: 45301 | C18: Outflow | D18: Rent | E18: Office | F18: Studio rent | G18: Main Bank | H18: Office Owner | I18: 18000 | J18: Paid | K18: Bank Transfer | L18: Historical demo | M18: =IF(B18="","",TEXT(B18,"mmm-yy")) -> Jan-24
A19: TXN-016 | B19: 45448 | C19: Inflow | D19: Sales | E19: Project | F19: Brand project milestone | G19: Main Bank | H19: Pixel Works | I19: 105000 | J19: Received | K19: Bank Transfer | L19: Historical demo | M19: =IF(B19="","",TEXT(B19,"mmm-yy")) -> Jun-24
A20: TXN-017 | B20: 45452 | C20: Outflow | D20: Marketing | E20: Ads | F20: Campaign spend | G20: Main Bank | H20: Meta | I20: 14000 | J20: Paid | K20: Card | L20: Historical demo | M20: =IF(B20="","",TEXT(B20,"mmm-yy")) -> Jun-24
A21: TXN-018 | B21: 45569 | C21: Inflow | D21: Services | E21: Consulting | F21: Growth workshop | G21: UPI | H21: Nexa Foods | I21: 65000 | J21: Received | K21: UPI | L21: Historical demo | M21: =IF(B21="","",TEXT(B21,"mmm-yy")) -> Oct-24
A22: TXN-019 | B22: 45572 | C22: Outflow | D22: Software | E22: Tools | F22: Software subscriptions | G22: Main Bank | H22: SaaS vendors | I22: 6800 | J22: Paid | K22: Card | L22: Historical demo | M22: =IF(B22="","",TEXT(B22,"mmm-yy")) -> Oct-24
A23: TXN-020 | B23: 45662 | C23: Inflow | D23: Services | E23: Retainer | F23: Acme Consulting — Jan | G23: Main Bank | H23: Acme Consulting | I23: 105000 | J23: Received | K23: Bank Transfer | L23: Historical demo | M23: =IF(B23="","",TEXT(B23,"mmm-yy")) -> Jan-25
A24: TXN-021 | B24: 45665 | C24: Outflow | D24: Salary | E24: Team | F24: Payroll | G24: Main Bank | H24: Team | I24: 60000 | J24: Paid | K24: Bank Transfer | L24: Historical demo | M24: =IF(B24="","",TEXT(B24,"mmm-yy")) -> Jan-25
A25: TXN-022 | B25: 45667 | C25: Outflow | D25: Rent | E25: Office | F25: Studio rent | G25: Main Bank | H25: Office Owner | I25: 22000 | J25: Paid | K25: Bank Transfer | L25: Historical demo | M25: =IF(B25="","",TEXT(B25,"mmm-yy")) -> Jan-25
A26: TXN-023 | B26: 45752 | C26: Inflow | D26: Sales | E26: Project | F26: Website project milestone | G26: Main Bank | H26: Bright Labs | I26: 135000 | J26: Received | K26: Bank Transfer | L26: Historical demo | M26: =IF(B26="","",TEXT(B26,"mmm-yy")) -> Apr-25
A27: TXN-024 | B27: 45756 | C27: Outflow | D27: Marketing | E27: Ads | F27: Campaign spend | G27: Main Bank | H27: Meta | I27: 21000 | J27: Paid | K27: Card | L27: Historical demo | M27: =IF(B27="","",TEXT(B27,"mmm-yy")) -> Apr-25
... A35: TXN-032 | B35: 46065 | C35: Outflow | D35: Travel | E35: Client | F35: Client workshop travel | G35: UPI | H35: Travel Desk | I35: 11000 | J35: Paid | K35: UPI | L35: Historical demo | M35: =IF(B35="","",TEXT(B35,"mmm-yy")) -> Feb-26
M36: =IF(B36="","",TEXT(B36,"mmm-yy"))
M37: =IF(B37="","",TEXT(B37,"mmm-yy"))
M38: =IF(B38="","",TEXT(B38,"mmm-yy"))
M39: =IF(B39="","",TEXT(B39,"mmm-yy"))
M40: =IF(B40="","",TEXT(B40,"mmm-yy"))
M41: =IF(B41="","",TEXT(B41,"mmm-yy"))
M42: =IF(B42="","",TEXT(B42,"mmm-yy"))
M43: =IF(B43="","",TEXT(B43,"mmm-yy"))
M44: =IF(B44="","",TEXT(B44,"mmm-yy"))
M45: =IF(B45="","",TEXT(B45,"mmm-yy"))
M46: =IF(B46="","",TEXT(B46,"mmm-yy"))
M47: =IF(B47="","",TEXT(B47,"mmm-yy"))
... M203: =IF(B203="","",TEXT(B203,"mmm-yy"))

Sheet 04_RECEIVABLES
A1: RECEIVABLES — WHO OWES YOU MONEY | B1: RECEIVABLES — WHO OWES YOU MONEY | C1: RECEIVABLES — WHO OWES YOU MONEY | D1: RECEIVABLES — WHO OWES YOU MONEY | E1: RECEIVABLES — WHO OWES YOU MONEY | F1: RECEIVABLES — WHO OWES YOU MONEY | G1: RECEIVABLES — WHO OWES YOU MONEY | H1: RECEIVABLES — WHO OWES YOU MONEY | I1: RECEIVABLES — WHO OWES YOU MONEY | J1: RECEIVABLES — WHO OWES YOU MONEY | K1: RECEIVABLES — WHO OWES YOU MONEY
A3: Invoice ID | B3: Customer | C3: Invoice Date | D3: Due Date | E3: Amount | F3: Amount Received | G3: Outstanding | H3: Status | I3: Days Overdue | J3: Expected Receipt | K3: Notes
A4: INV-001 | B4: Orbit Retail | C4: 46236 | D4: 46252 | E4: 95000 | F4: 25000 | G4: =E4-F4 -> 70000 | H4: =IF(D4="","",IF(G4=0,"Paid",IF(I4>0,"Overdue",IF(D4-'09_SETTINGS'!$I$5<='09_SETTINGS'!$I$8,"Due Soon","Outstanding")))) -> Overdue | I4: =IF(D4="","",MAX(0,'09_SETTINGS'!$I$8-D4)) -> 13 | J4: =IF(D4="","",D4) -> 46252
A5: INV-002 | B5: Bright Labs | C5: 46244 | D5: 46262 | E5: 75000 | F5: 0 | G5: =E5-F5 -> 75000 | H5: =IF(D5="","",IF(G5=0,"Paid",IF(I5>0,"Overdue",IF(D5-'09_SETTINGS'!$I$5<='09_SETTINGS'!$I$8,"Due Soon","Outstanding")))) -> Overdue | I5: =IF(D5="","",MAX(0,'09_SETTINGS'!$I$8-D5)) -> 3 | J5: =IF(D5="","",D5) -> 46262
A6: INV-003 | B6: Nexa Foods | C6: 46208 | D6: 46228 | E6: 60000 | F6: 0 | G6: =E6-F6 -> 60000 | H6: =IF(D6="","",IF(G6=0,"Paid",IF(I6>0,"Overdue",IF(D6-'09_SETTINGS'!$I$5<='09_SETTINGS'!$I$8,"Due Soon","Outstanding")))) -> Overdue | I6: =IF(D6="","",MAX(0,'09_SETTINGS'!$I$8-D6)) -> 37 | J6: =IF(D6="","",D6) -> 46228
A7: INV-004 | B7: Acme Consulting | C7: 46249 | D7: 46270 | E7: 120000 | F7: 0 | G7: =E7-F7 -> 120000 | H7: =IF(D7="","",IF(G7=0,"Paid",IF(I7>0,"Overdue",IF(D7-'09_SETTINGS'!$I$5<='09_SETTINGS'!$I$8,"Due Soon","Outstanding")))) -> Due Soon | I7: =IF(D7="","",MAX(0,'09_SETTINGS'!$I$8-D7)) -> 0 | J7: =IF(D7="","",D7) -> 46270
A8: INV-005 | B8: Pixel Works | C8: 46193 | D8: 46208 | E8: 40000 | F8: 0 | G8: =E8-F8 -> 40000 | H8: =IF(D8="","",IF(G8=0,"Paid",IF(I8>0,"Overdue",IF(D8-'09_SETTINGS'!$I$5<='09_SETTINGS'!$I$8,"Due Soon","Outstanding")))) -> Overdue | I8: =IF(D8="","",MAX(0,'09_SETTINGS'!$I$8-D8)) -> 57 | J8: =IF(D8="","",D8) -> 46208
G9: =E9-F9 -> 0 | H9: =IF(D9="","",IF(G9=0,"Paid",IF(I9>0,"Overdue",IF(D9-'09_SETTINGS'!$I$5<='09_SETTINGS'!$I$8,"Due Soon","Outstanding")))) | I9: =IF(D9="","",MAX(0,'09_SETTINGS'!$I$8-D9)) | J9: =IF(D9="","",D9)
G10: =E10-F10 -> 0 | H10: =IF(D10="","",IF(G10=0,"Paid",IF(I10>0,"Overdue",IF(D10-'09_SETTINGS'!$I$5<='09_SETTINGS'!$I$8,"Due Soon","Outstanding")))) | I10: =IF(D10="","",MAX(0,'09_SETTINGS'!$I$8-D10)) | J10: =IF(D10="","",D10)
G11: =E11-F11 -> 0 | H11: =IF(D11="","",IF(G11=0,"Paid",IF(I11>0,"Overdue",IF(D11-'09_SETTINGS'!$I$5<='09_SETTINGS'!$I$8,"Due Soon","Outstanding")))) | I11: =IF(D11="","",MAX(0,'09_SETTINGS'!$I$8-D11)) | J11: =IF(D11="","",D11)
G12: =E12-F12 -> 0 | H12: =IF(D12="","",IF(G12=0,"Paid",IF(I12>0,"Overdue",IF(D12-'09_SETTINGS'!$I$5<='09_SETTINGS'!$I$8,"Due Soon","Outstanding")))) | I12: =IF(D12="","",MAX(0,'09_SETTINGS'!$I$8-D12)) | J12: =IF(D12="","",D12)
G13: =E13-F13 -> 0 | H13: =IF(D13="","",IF(G13=0,"Paid",IF(I13>0,"Overdue",IF(D13-'09_SETTINGS'!$I$5<='09_SETTINGS'!$I$8,"Due Soon","Outstanding")))) | I13: =IF(D13="","",MAX(0,'09_SETTINGS'!$I$8-D13)) | J13: =IF(D13="","",D13)
G14: =E14-F14 -> 0 | H14: =IF(D14="","",IF(G14=0,"Paid",IF(I14>0,"Overdue",IF(D14-'09_SETTINGS'!$I$5<='09_SETTINGS'!$I$8,"Due Soon","Outstanding")))) | I14: =IF(D14="","",MAX(0,'09_SETTINGS'!$I$8-D14)) | J14: =IF(D14="","",D14)
G15: =E15-F15 -> 0 | H15: =IF(D15="","",IF(G15=0,"Paid",IF(I15>0,"Overdue",IF(D15-'09_SETTINGS'!$I$5<='09_SETTINGS'!$I$8,"Due Soon","Outstanding")))) | I15: =IF(D15="","",MAX(0,'09_SETTINGS'!$I$8-D15)) | J15: =IF(D15="","",D15)
G16: =E16-F16 -> 0 | H16: =IF(D16="","",IF(G16=0,"Paid",IF(I16>0,"Overdue",IF(D16-'09_SETTINGS'!$I$5<='09_SETTINGS'!$I$8,"Due Soon","Outstanding")))) | I16: =IF(D16="","",MAX(0,'09_SETTINGS'!$I$8-D16)) | J16: =IF(D16="","",D16)
G17: =E17-F17 -> 0 | H17: =IF(D17="","",IF(G17=0,"Paid",IF(I17>0,"Overdue",IF(D17-'09_SETTINGS'!$I$5<='09_SETTINGS'!$I$8,"Due Soon","Outstanding")))) | I17: =IF(D17="","",MAX(0,'09_SETTINGS'!$I$8-D17)) | J17: =IF(D17="","",D17)
G18: =E18-F18 -> 0 | H18: =IF(D18="","",IF(G18=0,"Paid",IF(I18>0,"Overdue",IF(D18-'09_SETTINGS'!$I$5<='09_SETTINGS'!$I$8,"Due Soon","Outstanding")))) | I18: =IF(D18="","",MAX(0,'09_SETTINGS'!$I$8-D18)) | J18: =IF(D18="","",D18)
G19: =E19-F19 -> 0 | H19: =IF(D19="","",IF(G19=0,"Paid",IF(I19>0,"Overdue",IF(D19-'09_SETTINGS'!$I$5<='09_SETTINGS'!$I$8,"Due Soon","Outstanding")))) | I19: =IF(D19="","",MAX(0,'09_SETTINGS'!$I$8-D19)) | J19: =IF(D19="","",D19)
G20: =E20-F20 -> 0 | H20: =IF(D20="","",IF(G20=0,"Paid",IF(I20>0,"Overdue",IF(D20-'09_SETTINGS'!$I$5<='09_SETTINGS'!$I$8,"Due Soon","Outstanding")))) | I20: =IF(D20="","",MAX(0,'09_SETTINGS'!$I$8-D20)) | J20: =IF(D20="","",D20)
... G203: =E203-F203 -> 0 | H203: =IF(D203="","",IF(G203=0,"Paid",IF(I203>0,"Overdue",IF(D203-'09_SETTINGS'!$I$5<='09_SETTINGS'!$I$8,"Due Soon","Outstanding")))) | I203: =IF(D203="","",MAX(0,'09_SETTINGS'!$I$8-D203)) | J203: =IF(D203="","",D203)

Sheet 05_PAYABLES
A1: PAYABLES — WHAT YOU NEED TO PAY | B1: PAYABLES — WHAT YOU NEED TO PAY | C1: PAYABLES — WHAT YOU NEED TO PAY | D1: PAYABLES — WHAT YOU NEED TO PAY | E1: PAYABLES — WHAT YOU NEED TO PAY | F1: PAYABLES — WHAT YOU NEED TO PAY | G1: PAYABLES — WHAT YOU NEED TO PAY | H1: PAYABLES — WHAT YOU NEED TO PAY | I1: PAYABLES — WHAT YOU NEED TO PAY | J1: PAYABLES — WHAT YOU NEED TO PAY
A3: Vendor | B3: Bill Date | C3: Due Date | D3: Amount | E3: Paid | F3: Outstanding | G3: Category | H3: Priority | I3: Status | J3: Notes
A4: Office Owner | B4: 46235 | C4: 46266 | D4: 25000 | E4: 0 | F4: =D4-E4 -> 25000 | G4: Rent | H4: High | I4: =IF(C4="","",IF(F4=0,"Paid",IF(C4<'09_SETTINGS'!$I$8,"Overdue",IF(C4-'09_SETTINGS'!$I$5<='09_SETTINGS'!$I$8,"Upcoming","Scheduled")))) -> Upcoming
A5: Freelancer Team | B5: 46254 | C5: 46270 | D5: 40000 | E5: 0 | F5: =D5-E5 -> 40000 | G5: Salary | H5: High | I5: =IF(C5="","",IF(F5=0,"Paid",IF(C5<'09_SETTINGS'!$I$8,"Overdue",IF(C5-'09_SETTINGS'!$I$5<='09_SETTINGS'!$I$8,"Upcoming","Scheduled")))) -> Upcoming
A6: Canva | B6: 46249 | C6: 46275 | D6: 4200 | E6: 0 | F6: =D6-E6 -> 4200 | G6: Software | H6: Medium | I6: =IF(C6="","",IF(F6=0,"Paid",IF(C6<'09_SETTINGS'!$I$8,"Overdue",IF(C6-'09_SETTINGS'!$I$5<='09_SETTINGS'!$I$8,"Upcoming","Scheduled")))) -> Scheduled
A7: GST Provision | B7: 46265 | C7: 46285 | D7: 38000 | E7: 0 | F7: =D7-E7 -> 38000 | G7: Taxes | H7: High | I7: =IF(C7="","",IF(F7=0,"Paid",IF(C7<'09_SETTINGS'!$I$8,"Overdue",IF(C7-'09_SETTINGS'!$I$5<='09_SETTINGS'!$I$8,"Upcoming","Scheduled")))) -> Scheduled
A8: Meta Ads | B8: 46259 | C8: 46280 | D8: 22000 | E8: 0 | F8: =D8-E8 -> 22000 | G8: Marketing | H8: Medium | I8: =IF(C8="","",IF(F8=0,"Paid",IF(C8<'09_SETTINGS'!$I$8,"Overdue",IF(C8-'09_SETTINGS'!$I$5<='09_SETTINGS'!$I$8,"Upcoming","Scheduled")))) -> Scheduled
F9: =D9-E9 -> 0 | I9: =IF(C9="","",IF(F9=0,"Paid",IF(C9<'09_SETTINGS'!$I$8,"Overdue",IF(C9-'09_SETTINGS'!$I$5<='09_SETTINGS'!$I$8,"Upcoming","Scheduled"))))
F10: =D10-E10 -> 0 | I10: =IF(C10="","",IF(F10=0,"Paid",IF(C10<'09_SETTINGS'!$I$8,"Overdue",IF(C10-'09_SETTINGS'!$I$5<='09_SETTINGS'!$I$8,"Upcoming","Scheduled"))))
F11: =D11-E11 -> 0 | I11: =IF(C11="","",IF(F11=0,"Paid",IF(C11<'09_SETTINGS'!$I$8,"Overdue",IF(C11-'09_SETTINGS'!$I$5<='09_SETTINGS'!$I$8,"Upcoming","Scheduled"))))
F12: =D12-E12 -> 0 | I12: =IF(C12="","",IF(F12=0,"Paid",IF(C12<'09_SETTINGS'!$I$8,"Overdue",IF(C12-'09_SETTINGS'!$I$5<='09_SETTINGS'!$I$8,"Upcoming","Scheduled"))))
F13: =D13-E13 -> 0 | I13: =IF(C13="","",IF(F13=0,"Paid",IF(C13<'09_SETTINGS'!$I$8,"Overdue",IF(C13-'09_SETTINGS'!$I$5<='09_SETTINGS'!$I$8,"Upcoming","Scheduled"))))
F14: =D14-E14 -> 0 | I14: =IF(C14="","",IF(F14=0,"Paid",IF(C14<'09_SETTINGS'!$I$8,"Overdue",IF(C14-'09_SETTINGS'!$I$5<='09_SETTINGS'!$I$8,"Upcoming","Scheduled"))))
F15: =D15-E15 -> 0 | I15: =IF(C15="","",IF(F15=0,"Paid",IF(C15<'09_SETTINGS'!$I$8,"Overdue",IF(C15-'09_SETTINGS'!$I$5<='09_SETTINGS'!$I$8,"Upcoming","Scheduled"))))
F16: =D16-E16 -> 0 | I16: =IF(C16="","",IF(F16=0,"Paid",IF(C16<'09_SETTINGS'!$I$8,"Overdue",IF(C16-'09_SETTINGS'!$I$5<='09_SETTINGS'!$I$8,"Upcoming","Scheduled"))))
F17: =D17-E17 -> 0 | I17: =IF(C17="","",IF(F17=0,"Paid",IF(C17<'09_SETTINGS'!$I$8,"Overdue",IF(C17-'09_SETTINGS'!$I$5<='09_SETTINGS'!$I$8,"Upcoming","Scheduled"))))
F18: =D18-E18 -> 0 | I18: =IF(C18="","",IF(F18=0,"Paid",IF(C18<'09_SETTINGS'!$I$8,"Overdue",IF(C18-'09_SETTINGS'!$I$5<='09_SETTINGS'!$I$8,"Upcoming","Scheduled"))))
F19: =D19-E19 -> 0 | I19: =IF(C19="","",IF(F19=0,"Paid",IF(C19<'09_SETTINGS'!$I$8,"Overdue",IF(C19-'09_SETTINGS'!$I$5<='09_SETTINGS'!$I$8,"Upcoming","Scheduled"))))
F20: =D20-E20 -> 0 | I20: =IF(C20="","",IF(F20=0,"Paid",IF(C20<'09_SETTINGS'!$I$8,"Overdue",IF(C20-'09_SETTINGS'!$I$5<='09_SETTINGS'!$I$8,"Upcoming","Scheduled"))))
... F203: =D203-E203 -> 0 | I203: =IF(C203="","",IF(F203=0,"Paid",IF(C203<'09_SETTINGS'!$I$8,"Overdue",IF(C203-'09_SETTINGS'!$I$5<='09_SETTINGS'!$I$8,"Upcoming","Scheduled"))))

Sheet 06_RECURRING
A1: RECURRING — CONTRACTED & REPEAT CASH FLOWS | B1: RECURRING — CONTRACTED & REPEAT CASH FLOWS | C1: RECURRING — CONTRACTED & REPEAT CASH FLOWS | D1: RECURRING — CONTRACTED & REPEAT CASH FLOWS | E1: RECURRING — CONTRACTED & REPEAT CASH FLOWS | F1: RECURRING — CONTRACTED & REPEAT CASH FLOWS | G1: RECURRING — CONTRACTED & REPEAT CASH FLOWS | H1: RECURRING — CONTRACTED & REPEAT CASH FLOWS | I1: RECURRING — CONTRACTED & REPEAT CASH FLOWS
A3: Item | B3: Type | C3: Category | D3: Amount | E3: Frequency | F3: Start Date | G3: Next Date | H3: Active | I3: Confidence
A4: Office rent | B4: Outflow | C4: Rent | D4: 25000 | E4: Monthly | F4: 46113 | G4: 46266 | H4: Yes | I4: High
A5: Canva + tools | B5: Outflow | C5: Software | D5: 4200 | E5: Monthly | F5: 46127 | G5: 46280 | H5: Yes | I5: High
A6: Acme retainer | B6: Inflow | C6: Services | D6: 120000 | E6: Monthly | F6: 46117 | G6: 46270 | H6: Yes | I6: High
A7: Payroll | B7: Outflow | C7: Salary | D7: 75000 | E7: Monthly | F7: 46115 | G7: 46268 | H7: Yes | I7: High
A8: Meta ads baseline | B8: Outflow | C8: Marketing | D8: 18000 | E8: Monthly | F8: 46122 | G8: 46275 | H8: Yes | I8: Medium
A9: Nexa support | B9: Inflow | C9: Services | D9: 35000 | E9: Monthly | F9: 46154 | G9: 46277 | H9: Yes | I9: Medium

Sheet 07_FORECAST
A1: 90-DAY CASH FORECAST | B1: 90-DAY CASH FORECAST | C1: 90-DAY CASH FORECAST | D1: 90-DAY CASH FORECAST | E1: 90-DAY CASH FORECAST | F1: 90-DAY CASH FORECAST | G1: 90-DAY CASH FORECAST | H1: 90-DAY CASH FORECAST
A2: High confidence = recurring/contracted; Medium confidence = expected customer payment. Forecast is a cash-management estimate, not a guarantee.
A4: Month | B4: Opening Cash | C4: Recurring Inflows | D4: Expected Receivables | E4: Recurring Outflows | F4: Expected Payables | G4: Net Cash Flow | H4: Projected Closing Cash
A5: 46235 | B5: ='01_START_HERE'!$G$12+SUMIFS('03_TRANSACTIONS'!$I$4:$I$203,'03_TRANSACTIONS'!$C$4:$C$203,"Inflow",'03_TRANSACTIONS'!$B$4:$B$203,"<="&'09_SETTINGS'!$I$8)-SUMIFS('03_TRANSACTIONS'!$I$4:$I$203,'03_TRANSACTIONS'!$C$4:$C$203,"Outflow",'03_TRANSACTIONS'!$B$4:$B$203,"<="&'09_SETTINGS'!$I$8) -> 1440000 | C5: =SUMIFS('06_RECURRING'!$D$4:$D$203,'06_RECURRING'!$B$4:$B$203,"Inflow",'06_RECURRING'!$H$4:$H$203,"Yes") -> 155000 | D5: =SUMIFS('04_RECEIVABLES'!$G$4:$G$203,'04_RECEIVABLES'!$J$4:$J$203,">="&A5,'04_RECEIVABLES'!$J$4:$J$203,"<"&EDATE(A5,1)) -> 145000 | E5: =SUMIFS('06_RECURRING'!$D$4:$D$203,'06_RECURRING'!$B$4:$B$203,"Outflow",'06_RECURRING'!$H$4:$H$203,"Yes") -> 122200 | F5: =SUMIFS('05_PAYABLES'!$F$4:$F$203,'05_PAYABLES'!$C$4:$C$203,">="&A5,'05_PAYABLES'!$C$4:$C$203,"<"&EDATE(A5,1)) -> 0 | G5: =C5+D5-E5-F5 -> 177800 | H5: =B5+G5 -> 1617800
A6: 46266 | B6: =H5 -> 1617800 | C6: =SUMIFS('06_RECURRING'!$D$4:$D$203,'06_RECURRING'!$B$4:$B$203,"Inflow",'06_RECURRING'!$H$4:$H$203,"Yes") -> 155000 | D6: =SUMIFS('04_RECEIVABLES'!$G$4:$G$203,'04_RECEIVABLES'!$J$4:$J$203,">="&A6,'04_RECEIVABLES'!$J$4:$J$203,"<"&EDATE(A6,1)) -> 120000 | E6: =SUMIFS('06_RECURRING'!$D$4:$D$203,'06_RECURRING'!$B$4:$B$203,"Outflow",'06_RECURRING'!$H$4:$H$203,"Yes") -> 122200 | F6: =SUMIFS('05_PAYABLES'!$F$4:$F$203,'05_PAYABLES'!$C$4:$C$203,">="&A6,'05_PAYABLES'!$C$4:$C$203,"<"&EDATE(A6,1)) -> 129200 | G6: =C6+D6-E6-F6 -> 23600 | H6: =B6+G6 -> 1641400
A7: 46296 | B7: =H6 -> 1641400 | C7: =SUMIFS('06_RECURRING'!$D$4:$D$203,'06_RECURRING'!$B$4:$B$203,"Inflow",'06_RECURRING'!$H$4:$H$203,"Yes") -> 155000 | D7: =SUMIFS('04_RECEIVABLES'!$G$4:$G$203,'04_RECEIVABLES'!$J$4:$J$203,">="&A7,'04_RECEIVABLES'!$J$4:$J$203,"<"&EDATE(A7,1)) -> 0 | E7: =SUMIFS('06_RECURRING'!$D$4:$D$203,'06_RECURRING'!$B$4:$B$203,"Outflow",'06_RECURRING'!$H$4:$H$203,"Yes") -> 122200 | F7: =SUMIFS('05_PAYABLES'!$F$4:$F$203,'05_PAYABLES'!$C$4:$C$203,">="&A7,'05_PAYABLES'!$C$4:$C$203,"<"&EDATE(A7,1)) -> 0 | G7: =C7+D7-E7-F7 -> 32800 | H7: =B7+G7 -> 1674200
A10: CASH SAFETY CHECK | B10: CASH SAFETY CHECK | C10: CASH SAFETY CHECK | D10: CASH SAFETY CHECK
A11: Minimum Cash Threshold | B11: ='09_SETTINGS'!$I$4 -> 200000
A12: Lowest Projected Cash | B12: =MIN(H5:H7) -> 1617800
A13: Cash Pressure | B13: =IF(B12<B11,"WARNING — projected cash below threshold","SAFE — projected cash above threshold") -> SAFE — projected cash above threshold
A14: Cash Runway (months) | B14: =IFERROR(B5/'08_ANALYSIS'!$B$5,0) -> 11.483254

Sheet 08_ANALYSIS
A1: ANALYSIS — WHAT IS CHANGING | B1: ANALYSIS — WHAT IS CHANGING | C1: ANALYSIS — WHAT IS CHANGING | D1: ANALYSIS — WHAT IS CHANGING | E1: ANALYSIS — WHAT IS CHANGING | F1: ANALYSIS — WHAT IS CHANGING | G1: ANALYSIS — WHAT IS CHANGING | H1: ANALYSIS — WHAT IS CHANGING
A3: Metric | B3: Current Month | C3: Previous Month | D3: Change
A4: Inflow | B4: =SUMIFS('03_TRANSACTIONS'!$I$4:$I$203,'03_TRANSACTIONS'!$C$4:$C$203,"Inflow",'03_TRANSACTIONS'!$B$4:$B$203,">="&DATE(YEAR('09_SETTINGS'!$I$8),MONTH('09_SETTINGS'!$I$8),1),'03_TRANSACTIONS'!$B$4:$B$203,"<="&'09_SETTINGS'!$I$8) -> 240000 | C4: =SUMIFS('03_TRANSACTIONS'!$I$4:$I$203,'03_TRANSACTIONS'!$C$4:$C$203,"Inflow",'03_TRANSACTIONS'!$M$4:$M$203,TEXT(EDATE('09_SETTINGS'!$I$8,-1),"mmm-yy")) -> 115000 | D4: =IFERROR(B4/C4-1,0) -> 1.0869565
A5: Outflow | B5: =SUMIFS('03_TRANSACTIONS'!$I$4:$I$203,'03_TRANSACTIONS'!$C$4:$C$203,"Outflow",'03_TRANSACTIONS'!$B$4:$B$203,">="&DATE(YEAR('09_SETTINGS'!$I$8),MONTH('09_SETTINGS'!$I$8),1),'03_TRANSACTIONS'!$B$4:$B$203,"<="&'09_SETTINGS'!$I$8) -> 125400 | C5: =SUMIFS('03_TRANSACTIONS'!$I$4:$I$203,'03_TRANSACTIONS'!$C$4:$C$203,"Outflow",'03_TRANSACTIONS'!$M$4:$M$203,TEXT(EDATE('09_SETTINGS'!$I$8,-1),"mmm-yy")) -> 109000 | D5: =IFERROR(B5/C5-1,0) -> 0.15045872
A6: Net Cash Flow | B6: =B4-B5 -> 114600 | C6: =C4-C5 -> 6000 | D6: =IFERROR(B6/C6-1,0) -> 18.1
A7: Receivables | B7: =SUM('04_RECEIVABLES'!$G$4:$G$203) -> 365000 | C7: ="N/A" -> N/A | D7: =IFERROR(B7/C7-1,0) -> 0
A10: EXPENSE TREND | B10: EXPENSE TREND | C10: EXPENSE TREND | D10: EXPENSE TREND
A11: Category | B11: Current Month | C11: Previous Month | D11: Change
A12: Salary | B12: =SUMIFS('03_TRANSACTIONS'!$I$4:$I$203,'03_TRANSACTIONS'!$D$4:$D$203,A12,'03_TRANSACTIONS'!$C$4:$C$203,"Outflow",'03_TRANSACTIONS'!$B$4:$B$203,">="&DATE(YEAR('09_SETTINGS'!$I$8),MONTH('09_SETTINGS'!$I$8),1),'03_TRANSACTIONS'!$B$4:$B$203,"<="&'09_SETTINGS'!$I$8) -> 75000 | C12: =SUMIFS('03_TRANSACTIONS'!$I$4:$I$203,'03_TRANSACTIONS'!$D$4:$D$203,A12,'03_TRANSACTIONS'!$C$4:$C$203,"Outflow",'03_TRANSACTIONS'!$M$4:$M$203,TEXT(EDATE('09_SETTINGS'!$I$8,-1),"mmm-yy")) -> 72000 | D12: =IFERROR(B12/C12-1,0) -> 0.041666667
A13: Rent | B13: =SUMIFS('03_TRANSACTIONS'!$I$4:$I$203,'03_TRANSACTIONS'!$D$4:$D$203,A13,'03_TRANSACTIONS'!$C$4:$C$203,"Outflow",'03_TRANSACTIONS'!$B$4:$B$203,">="&DATE(YEAR('09_SETTINGS'!$I$8),MONTH('09_SETTINGS'!$I$8),1),'03_TRANSACTIONS'!$B$4:$B$203,"<="&'09_SETTINGS'!$I$8) -> 25000 | C13: =SUMIFS('03_TRANSACTIONS'!$I$4:$I$203,'03_TRANSACTIONS'!$D$4:$D$203,A13,'03_TRANSACTIONS'!$C$4:$C$203,"Outflow",'03_TRANSACTIONS'!$M$4:$M$203,TEXT(EDATE('09_SETTINGS'!$I$8,-1),"mmm-yy")) -> 25000 | D13: =IFERROR(B13/C13-1,0) -> 0
A14: Marketing | B14: =SUMIFS('03_TRANSACTIONS'!$I$4:$I$203,'03_TRANSACTIONS'!$D$4:$D$203,A14,'03_TRANSACTIONS'!$C$4:$C$203,"Outflow",'03_TRANSACTIONS'!$B$4:$B$203,">="&DATE(YEAR('09_SETTINGS'!$I$8),MONTH('09_SETTINGS'!$I$8),1),'03_TRANSACTIONS'!$B$4:$B$203,"<="&'09_SETTINGS'!$I$8) -> 18000 | C14: =SUMIFS('03_TRANSACTIONS'!$I$4:$I$203,'03_TRANSACTIONS'!$D$4:$D$203,A14,'03_TRANSACTIONS'!$C$4:$C$203,"Outflow",'03_TRANSACTIONS'!$M$4:$M$203,TEXT(EDATE('09_SETTINGS'!$I$8,-1),"mmm-yy")) -> 12000 | D14: =IFERROR(B14/C14-1,0) -> 0.5
A15: Software | B15: =SUMIFS('03_TRANSACTIONS'!$I$4:$I$203,'03_TRANSACTIONS'!$D$4:$D$203,A15,'03_TRANSACTIONS'!$C$4:$C$203,"Outflow",'03_TRANSACTIONS'!$B$4:$B$203,">="&DATE(YEAR('09_SETTINGS'!$I$8),MONTH('09_SETTINGS'!$I$8),1),'03_TRANSACTIONS'!$B$4:$B$203,"<="&'09_SETTINGS'!$I$8) -> 4200 | C15: =SUMIFS('03_TRANSACTIONS'!$I$4:$I$203,'03_TRANSACTIONS'!$D$4:$D$203,A15,'03_TRANSACTIONS'!$C$4:$C$203,"Outflow",'03_TRANSACTIONS'!$M$4:$M$203,"mmm-yy") -> 0 | D15: =IFERROR(B15/C15-1,0) -> 0
A16: Travel | B16: =SUMIFS('03_TRANSACTIONS'!$I$4:$I$203,'03_TRANSACTIONS'!$D$4:$D$203,A16,'03_TRANSACTIONS'!$C$4:$C$203,"Outflow",'03_TRANSACTIONS'!$B$4:$B$203,">="&DATE(YEAR('09_SETTINGS'!$I$8),MONTH('09_SETTINGS'!$I$8),1),'03_TRANSACTIONS'!$B$4:$B$203,"<="&'09_SETTINGS'!$I$8) -> 0 | C16: =SUMIFS('03_TRANSACTIONS'!$I$4:$I$203,'03_TRANSACTIONS'!$D$4:$D$203,A16,'03_TRANSACTIONS'!$C$4:$C$203,"Outflow",'03_TRANSACTIONS'!$M$4:$M$203,"mmm-yy") -> 0 | D16: =IFERROR(B16/C16-1,0) -> 0

Sheet 09_SETTINGS
A1: SETTINGS & CONTROL LISTS | B1: SETTINGS & CONTROL LISTS | C1: SETTINGS & CONTROL LISTS | D1: SETTINGS & CONTROL LISTS | E1: SETTINGS & CONTROL LISTS | F1: SETTINGS & CONTROL LISTS | G1: SETTINGS & CONTROL LISTS | H1: SETTINGS & CONTROL LISTS
A3: Income Categories | B3: Expense Categories | D3: Accounts | F3: Payment Methods | H3: Thresholds | K3: Lists | L3: Priority | M3: Frequency
A4: Sales | B4: Salary | D4: Main Bank | F4: Bank Transfer | H4: Minimum Cash Threshold | I4: 200000 | K4: Inflow | L4: High | M4: Weekly
A5: Services | B5: Rent | D5: Savings | F5: UPI | H5: Receivable Warning Days | I5: 7 | K5: Outflow | L5: Medium | M5: Monthly
A6: Interest | B6: Marketing | D6: Cash | F6: Cash | H6: Expense Growth Alert % | I6: 0.2 | K6: Received | L6: Low | M6: Quarterly
A7: Other Income | B7: Software | D7: UPI | F7: Card | H7: Forecast Period (days) | I7: 90 | K7: Paid | M7: Yearly
B8: Utilities | D8: Credit Card | F8: Cheque | H8: Report Date | I8: 46265 | K8: Pending
B9: Travel | D9: Other | K9: Yes
B10: Office
B11: Supplies
B12: Taxes
B13: Loan
B14: Bank Charges
B15: Other
